[
  {
    "company_name": "QUAKER CHEMICAL CORP",
    "industry": "Specialty Chemicals",
    "company_size": "large",
    "stage": "public",
    "workforce_count": 4700,
    "open_jobs_count": 0,
    "financial_signals": {
      "burn_rate": "moderate",
      "funding_stage": "Public (NASDAQ/NYSE)",
      "revenue_trend": "stable",
      "months_since_last_funding": 120
    },
    "layoff_history": {
      "total_layoffs": 0,
      "last_layoff_date": "No History",
      "layoff_frequency": "none",
      "affected_departments": []
    },
    "hiring_signals": {
      "hiring_velocity": "moderate",
      "hiring_freeze_score": 0.1
    },
    "role_risk_map": {
      "sales": 0.1,
      "designer": 0.1,
      "hr_recruiter": 0.1,
      "data_scientist": 0.1,
      "product_manager": 0.1,
      "software_engineer": 0.1
    },
    "ai_exposure_index": 0.5,
    "market_risk_score": 0.15,
    "company_risk_score": 0.1,
    "confidence_score": 0.95,
    "archetype": "mature_stable",
    "data_source": "expansion_batch_2026_real",
    "last_updated": "2026-04-28"
  },
  {
    "company_name": "WisdomTree, Inc.",
    "industry": "Asset Management",
    "company_size": "mid",
    "stage": "public",
    "workforce_count": 360,
    "open_jobs_count": 0,
    "financial_signals": {
      "burn_rate": "moderate",
      "funding_stage": "Public (NASDAQ/NYSE)",
      "revenue_trend": "stable",
      "months_since_last_funding": 120
    },
    "layoff_history": {
      "total_layoffs": 0,
      "last_layoff_date": "No History",
      "layoff_frequency": "none",
      "affected_departments": []
    },
    "hiring_signals": {
      "hiring_velocity": "moderate",
      "hiring_freeze_score": 0.1
    },
    "role_risk_map": {
      "sales": 0.1,
      "designer": 0.1,
      "hr_recruiter": 0.1,
      "data_scientist": 0.1,
      "product_manager": 0.1,
      "software_engineer": 0.1
    },
    "ai_exposure_index": 0.5,
    "market_risk_score": 0.15,
    "company_risk_score": 0.1,
    "confidence_score": 0.95,
    "archetype": "mature_stable",
    "data_source": "expansion_batch_2026_real",
    "last_updated": "2026-04-28"
  },
  {
    "company_name": "Acadian Asset Management Inc.",
    "industry": "Asset Management",
    "company_size": "mid",
    "stage": "public",
    "workforce_count": 396,
    "open_jobs_count": 0,
    "financial_signals": {
      "burn_rate": "moderate",
      "funding_stage": "Public (NASDAQ/NYSE)",
      "revenue_trend": "stable",
      "months_since_last_funding": 120
    },
    "layoff_history": {
      "total_layoffs": 0,
      "last_layoff_date": "No History",
      "layoff_frequency": "none",
      "affected_departments": []
    },
    "hiring_signals": {
      "hiring_velocity": "moderate",
      "hiring_freeze_score": 0.1
    },
    "role_risk_map": {
      "sales": 0.1,
      "designer": 0.1,
      "hr_recruiter": 0.1,
      "data_scientist": 0.1,
      "product_manager": 0.1,
      "software_engineer": 0.1
    },
    "ai_exposure_index": 0.5,
    "market_risk_score": 0.15,
    "company_risk_score": 0.1,
    "confidence_score": 0.95,
    "archetype": "mature_stable",
    "data_source": "expansion_batch_2026_real",
    "last_updated": "2026-04-28"
  },
  {
    "company_name": "SONIC AUTOMOTIVE INC",
    "industry": "Auto & Truck Dealerships",
    "company_size": "global_giant",
    "stage": "public",
    "workforce_count": 11000,
    "open_jobs_count": 0,
    "financial_signals": {
      "burn_rate": "moderate",
      "funding_stage": "Public (NASDAQ/NYSE)",
      "revenue_trend": "stable",
      "months_since_last_funding": 120
    },
    "layoff_history": {
      "total_layoffs": 0,
      "last_layoff_date": "No History",
      "layoff_frequency": "none",
      "affected_departments": []
    },
    "hiring_signals": {
      "hiring_velocity": "moderate",
      "hiring_freeze_score": 0.1
    },
    "role_risk_map": {
      "sales": 0.1,
      "designer": 0.1,
      "hr_recruiter": 0.1,
      "data_scientist": 0.1,
      "product_manager": 0.1,
      "software_engineer": 0.1
    },
    "ai_exposure_index": 0.5,
    "market_risk_score": 0.15,
    "company_risk_score": 0.1,
    "confidence_score": 0.95,
    "archetype": "mature_stable",
    "data_source": "expansion_batch_2026_real",
    "last_updated": "2026-04-28"
  },
  {
    "company_name": "Ultragenyx Pharmaceutical Inc.",
    "industry": "Biotechnology",
    "company_size": "large",
    "stage": "public",
    "workforce_count": 1371,
    "open_jobs_count": 0,
    "financial_signals": {
      "burn_rate": "moderate",
      "funding_stage": "Public (NASDAQ/NYSE)",
      "revenue_trend": "stable",
      "months_since_last_funding": 120
    },
    "layoff_history": {
      "total_layoffs": 0,
      "last_layoff_date": "No History",
      "layoff_frequency": "none",
      "affected_departments": []
    },
    "hiring_signals": {
      "hiring_velocity": "moderate",
      "hiring_freeze_score": 0.1
    },
    "role_risk_map": {
      "sales": 0.1,
      "designer": 0.1,
      "hr_recruiter": 0.1,
      "data_scientist": 0.1,
      "product_manager": 0.1,
      "software_engineer": 0.1
    },
    "ai_exposure_index": 0.5,
    "market_risk_score": 0.15,
    "company_risk_score": 0.1,
    "confidence_score": 0.95,
    "archetype": "mature_stable",
    "data_source": "expansion_batch_2026_real",
    "last_updated": "2026-04-28"
  },
  {
    "company_name": "HUTCHMED (China) Ltd",
    "industry": "Drug Manufacturers - Specialty & Generic",
    "company_size": "large",
    "stage": "public",
    "workforce_count": 1796,
    "open_jobs_count": 0,
    "financial_signals": {
      "burn_rate": "moderate",
      "funding_stage": "Public (NASDAQ/NYSE)",
      "revenue_trend": "stable",
      "months_since_last_funding": 120
    },
    "layoff_history": {
      "total_layoffs": 0,
      "last_layoff_date": "No History",
      "layoff_frequency": "none",
      "affected_departments": []
    },
    "hiring_signals": {
      "hiring_velocity": "moderate",
      "hiring_freeze_score": 0.1
    },
    "role_risk_map": {
      "sales": 0.1,
      "designer": 0.1,
      "hr_recruiter": 0.1,
      "data_scientist": 0.1,
      "product_manager": 0.1,
      "software_engineer": 0.1
    },
    "ai_exposure_index": 0.5,
    "market_risk_score": 0.15,
    "company_risk_score": 0.1,
    "confidence_score": 0.95,
    "archetype": "mature_stable",
    "data_source": "expansion_batch_2026_real",
    "last_updated": "2026-04-28"
  },
  {
    "company_name": "Delek US Holdings, Inc.",
    "industry": "Oil & Gas Refining & Marketing",
    "company_size": "large",
    "stage": "public",
    "workforce_count": 1902,
    "open_jobs_count": 0,
    "financial_signals": {
      "burn_rate": "moderate",
      "funding_stage": "Public (NASDAQ/NYSE)",
      "revenue_trend": "stable",
      "months_since_last_funding": 120
    },
    "layoff_history": {
      "total_layoffs": 0,
      "last_layoff_date": "No History",
      "layoff_frequency": "none",
      "affected_departments": []
    },
    "hiring_signals": {
      "hiring_velocity": "moderate",
      "hiring_freeze_score": 0.1
    },
    "role_risk_map": {
      "sales": 0.1,
      "designer": 0.1,
      "hr_recruiter": 0.1,
      "data_scientist": 0.1,
      "product_manager": 0.1,
      "software_engineer": 0.1
    },
    "ai_exposure_index": 0.5,
    "market_risk_score": 0.15,
    "company_risk_score": 0.1,
    "confidence_score": 0.95,
    "archetype": "mature_stable",
    "data_source": "expansion_batch_2026_real",
    "last_updated": "2026-04-28"
  },
  {
    "company_name": "ONESPAWORLD HOLDINGS Ltd",
    "industry": "Leisure",
    "company_size": "enterprise",
    "stage": "public",
    "workforce_count": 5395,
    "open_jobs_count": 0,
    "financial_signals": {
      "burn_rate": "moderate",
      "funding_stage": "Public (NASDAQ/NYSE)",
      "revenue_trend": "stable",
      "months_since_last_funding": 120
    },
    "layoff_history": {
      "total_layoffs": 0,
      "last_layoff_date": "No History",
      "layoff_frequency": "none",
      "affected_departments": []
    },
    "hiring_signals": {
      "hiring_velocity": "moderate",
      "hiring_freeze_score": 0.1
    },
    "role_risk_map": {
      "sales": 0.1,
      "designer": 0.1,
      "hr_recruiter": 0.1,
      "data_scientist": 0.1,
      "product_manager": 0.1,
      "software_engineer": 0.1
    },
    "ai_exposure_index": 0.5,
    "market_risk_score": 0.15,
    "company_risk_score": 0.1,
    "confidence_score": 0.95,
    "archetype": "mature_stable",
    "data_source": "expansion_batch_2026_real",
    "last_updated": "2026-04-28"
  },
  {
    "company_name": "National Energy Services Reunited Corp.",
    "industry": "Oil & Gas Equipment & Services",
    "company_size": "enterprise",
    "stage": "public",
    "workforce_count": 7352,
    "open_jobs_count": 0,
    "financial_signals": {
      "burn_rate": "moderate",
      "funding_stage": "Public (NASDAQ/NYSE)",
      "revenue_trend": "stable",
      "months_since_last_funding": 120
    },
    "layoff_history": {
      "total_layoffs": 0,
      "last_layoff_date": "No History",
      "layoff_frequency": "none",
      "affected_departments": []
    },
    "hiring_signals": {
      "hiring_velocity": "moderate",
      "hiring_freeze_score": 0.1
    },
    "role_risk_map": {
      "sales": 0.1,
      "designer": 0.1,
      "hr_recruiter": 0.1,
      "data_scientist": 0.1,
      "product_manager": 0.1,
      "software_engineer": 0.1
    },
    "ai_exposure_index": 0.5,
    "market_risk_score": 0.15,
    "company_risk_score": 0.1,
    "confidence_score": 0.95,
    "archetype": "mature_stable",
    "data_source": "expansion_batch_2026_real",
    "last_updated": "2026-04-28"
  },
  {
    "company_name": "Guardian Pharmacy Services, Inc.",
    "industry": "Medical Care Facilities",
    "company_size": "large",
    "stage": "public",
    "workforce_count": 3600,
    "open_jobs_count": 0,
    "financial_signals": {
      "burn_rate": "moderate",
      "funding_stage": "Public (NASDAQ/NYSE)",
      "revenue_trend": "stable",
      "months_since_last_funding": 120
    },
    "layoff_history": {
      "total_layoffs": 0,
      "last_layoff_date": "No History",
      "layoff_frequency": "none",
      "affected_departments": []
    },
    "hiring_signals": {
      "hiring_velocity": "moderate",
      "hiring_freeze_score": 0.1
    },
    "role_risk_map": {
      "sales": 0.1,
      "designer": 0.1,
      "hr_recruiter": 0.1,
      "data_scientist": 0.1,
      "product_manager": 0.1,
      "software_engineer": 0.1
    },
    "ai_exposure_index": 0.5,
    "market_risk_score": 0.15,
    "company_risk_score": 0.1,
    "confidence_score": 0.95,
    "archetype": "mature_stable",
    "data_source": "expansion_batch_2026_real",
    "last_updated": "2026-04-28"
  },
  {
    "company_name": "Ardagh Metal Packaging S.A.",
    "industry": "Packaging & Containers",
    "company_size": "enterprise",
    "stage": "public",
    "workforce_count": 6500,
    "open_jobs_count": 0,
    "financial_signals": {
      "burn_rate": "moderate",
      "funding_stage": "Public (NASDAQ/NYSE)",
      "revenue_trend": "stable",
      "months_since_last_funding": 120
    },
    "layoff_history": {
      "total_layoffs": 0,
      "last_layoff_date": "No History",
      "layoff_frequency": "none",
      "affected_departments": []
    },
    "hiring_signals": {
      "hiring_velocity": "moderate",
      "hiring_freeze_score": 0.1
    },
    "role_risk_map": {
      "sales": 0.1,
      "designer": 0.1,
      "hr_recruiter": 0.1,
      "data_scientist": 0.1,
      "product_manager": 0.1,
      "software_engineer": 0.1
    },
    "ai_exposure_index": 0.5,
    "market_risk_score": 0.15,
    "company_risk_score": 0.1,
    "confidence_score": 0.95,
    "archetype": "mature_stable",
    "data_source": "expansion_batch_2026_real",
    "last_updated": "2026-04-28"
  },
  {
    "company_name": "DENTSPLY SIRONA Inc.",
    "industry": "Medical Instruments & Supplies",
    "company_size": "global_giant",
    "stage": "public",
    "workforce_count": 14000,
    "open_jobs_count": 0,
    "financial_signals": {
      "burn_rate": "moderate",
      "funding_stage": "Public (NASDAQ/NYSE)",
      "revenue_trend": "stable",
      "months_since_last_funding": 120
    },
    "layoff_history": {
      "total_layoffs": 0,
      "last_layoff_date": "No History",
      "layoff_frequency": "none",
      "affected_departments": []
    },
    "hiring_signals": {
      "hiring_velocity": "moderate",
      "hiring_freeze_score": 0.1
    },
    "role_risk_map": {
      "sales": 0.1,
      "designer": 0.1,
      "hr_recruiter": 0.1,
      "data_scientist": 0.1,
      "product_manager": 0.1,
      "software_engineer": 0.1
    },
    "ai_exposure_index": 0.5,
    "market_risk_score": 0.15,
    "company_risk_score": 0.1,
    "confidence_score": 0.95,
    "archetype": "mature_stable",
    "data_source": "expansion_batch_2026_real",
    "last_updated": "2026-04-28"
  },
  {
    "company_name": "ICHOR HOLDINGS, LTD.",
    "industry": "Semiconductor Equipment & Materials",
    "company_size": "large",
    "stage": "public",
    "workforce_count": 1891,
    "open_jobs_count": 0,
    "financial_signals": {
      "burn_rate": "moderate",
      "funding_stage": "Public (NASDAQ/NYSE)",
      "revenue_trend": "stable",
      "months_since_last_funding": 120
    },
    "layoff_history": {
      "total_layoffs": 0,
      "last_layoff_date": "No History",
      "layoff_frequency": "none",
      "affected_departments": []
    },
    "hiring_signals": {
      "hiring_velocity": "moderate",
      "hiring_freeze_score": 0.1
    },
    "role_risk_map": {
      "sales": 0.1,
      "designer": 0.1,
      "hr_recruiter": 0.1,
      "data_scientist": 0.1,
      "product_manager": 0.1,
      "software_engineer": 0.1
    },
    "ai_exposure_index": 0.5,
    "market_risk_score": 0.15,
    "company_risk_score": 0.1,
    "confidence_score": 0.95,
    "archetype": "mature_stable",
    "data_source": "expansion_batch_2026_real",
    "last_updated": "2026-04-28"
  },
  {
    "company_name": "Aecon Group Inc.",
    "industry": "Engineering & Construction",
    "company_size": "enterprise",
    "stage": "public",
    "workforce_count": 8785,
    "open_jobs_count": 0,
    "financial_signals": {
      "burn_rate": "moderate",
      "funding_stage": "Public (NASDAQ/NYSE)",
      "revenue_trend": "stable",
      "months_since_last_funding": 120
    },
    "layoff_history": {
      "total_layoffs": 0,
      "last_layoff_date": "No History",
      "layoff_frequency": "none",
      "affected_departments": []
    },
    "hiring_signals": {
      "hiring_velocity": "moderate",
      "hiring_freeze_score": 0.1
    },
    "role_risk_map": {
      "sales": 0.1,
      "designer": 0.1,
      "hr_recruiter": 0.1,
      "data_scientist": 0.1,
      "product_manager": 0.1,
      "software_engineer": 0.1
    },
    "ai_exposure_index": 0.5,
    "market_risk_score": 0.15,
    "company_risk_score": 0.1,
    "confidence_score": 0.95,
    "archetype": "mature_stable",
    "data_source": "expansion_batch_2026_real",
    "last_updated": "2026-04-28"
  },
  {
    "company_name": "B&M European Value Retail S.A./ADR",
    "industry": "Discount Stores",
    "company_size": "global_giant",
    "stage": "public",
    "workforce_count": 39548,
    "open_jobs_count": 0,
    "financial_signals": {
      "burn_rate": "moderate",
      "funding_stage": "Public (NASDAQ/NYSE)",
      "revenue_trend": "stable",
      "months_since_last_funding": 120
    },
    "layoff_history": {
      "total_layoffs": 0,
      "last_layoff_date": "No History",
      "layoff_frequency": "none",
      "affected_departments": []
    },
    "hiring_signals": {
      "hiring_velocity": "moderate",
      "hiring_freeze_score": 0.1
    },
    "role_risk_map": {
      "sales": 0.1,
      "designer": 0.1,
      "hr_recruiter": 0.1,
      "data_scientist": 0.1,
      "product_manager": 0.1,
      "software_engineer": 0.1
    },
    "ai_exposure_index": 0.5,
    "market_risk_score": 0.15,
    "company_risk_score": 0.1,
    "confidence_score": 0.95,
    "archetype": "mature_stable",
    "data_source": "expansion_batch_2026_real",
    "last_updated": "2026-04-28"
  },
  {
    "company_name": "ABM INDUSTRIES INC /DE/",
    "industry": "Specialty Business Services",
    "company_size": "global_giant",
    "stage": "public",
    "workforce_count": 100000,
    "open_jobs_count": 0,
    "financial_signals": {
      "burn_rate": "moderate",
      "funding_stage": "Public (NASDAQ/NYSE)",
      "revenue_trend": "stable",
      "months_since_last_funding": 120
    },
    "layoff_history": {
      "total_layoffs": 0,
      "last_layoff_date": "No History",
      "layoff_frequency": "none",
      "affected_departments": []
    },
    "hiring_signals": {
      "hiring_velocity": "moderate",
      "hiring_freeze_score": 0.1
    },
    "role_risk_map": {
      "sales": 0.1,
      "designer": 0.1,
      "hr_recruiter": 0.1,
      "data_scientist": 0.1,
      "product_manager": 0.1,
      "software_engineer": 0.1
    },
    "ai_exposure_index": 0.5,
    "market_risk_score": 0.15,
    "company_risk_score": 0.1,
    "confidence_score": 0.95,
    "archetype": "mature_stable",
    "data_source": "expansion_batch_2026_real",
    "last_updated": "2026-04-28"
  },
  {
    "company_name": "NBT BANCORP INC",
    "industry": "Banks - Regional",
    "company_size": "large",
    "stage": "public",
    "workforce_count": 2303,
    "open_jobs_count": 0,
    "financial_signals": {
      "burn_rate": "moderate",
      "funding_stage": "Public (NASDAQ/NYSE)",
      "revenue_trend": "stable",
      "months_since_last_funding": 120
    },
    "layoff_history": {
      "total_layoffs": 0,
      "last_layoff_date": "No History",
      "layoff_frequency": "none",
      "affected_departments": []
    },
    "hiring_signals": {
      "hiring_velocity": "moderate",
      "hiring_freeze_score": 0.1
    },
    "role_risk_map": {
      "sales": 0.1,
      "designer": 0.1,
      "hr_recruiter": 0.1,
      "data_scientist": 0.1,
      "product_manager": 0.1,
      "software_engineer": 0.1
    },
    "ai_exposure_index": 0.5,
    "market_risk_score": 0.15,
    "company_risk_score": 0.1,
    "confidence_score": 0.95,
    "archetype": "mature_stable",
    "data_source": "expansion_batch_2026_real",
    "last_updated": "2026-04-28"
  },
  {
    "company_name": "CENTRAL GARDEN & PET CO",
    "industry": "Packaged Foods",
    "company_size": "enterprise",
    "stage": "public",
    "workforce_count": 6000,
    "open_jobs_count": 0,
    "financial_signals": {
      "burn_rate": "moderate",
      "funding_stage": "Public (NASDAQ/NYSE)",
      "revenue_trend": "stable",
      "months_since_last_funding": 120
    },
    "layoff_history": {
      "total_layoffs": 0,
      "last_layoff_date": "No History",
      "layoff_frequency": "none",
      "affected_departments": []
    },
    "hiring_signals": {
      "hiring_velocity": "moderate",
      "hiring_freeze_score": 0.1
    },
    "role_risk_map": {
      "sales": 0.1,
      "designer": 0.1,
      "hr_recruiter": 0.1,
      "data_scientist": 0.1,
      "product_manager": 0.1,
      "software_engineer": 0.1
    },
    "ai_exposure_index": 0.5,
    "market_risk_score": 0.15,
    "company_risk_score": 0.1,
    "confidence_score": 0.95,
    "archetype": "mature_stable",
    "data_source": "expansion_batch_2026_real",
    "last_updated": "2026-04-28"
  },
  {
    "company_name": "Huntsman CORP",
    "industry": "Chemicals",
    "company_size": "enterprise",
    "stage": "public",
    "workforce_count": 6000,
    "open_jobs_count": 0,
    "financial_signals": {
      "burn_rate": "moderate",
      "funding_stage": "Public (NASDAQ/NYSE)",
      "revenue_trend": "stable",
      "months_since_last_funding": 120
    },
    "layoff_history": {
      "total_layoffs": 0,
      "last_layoff_date": "No History",
      "layoff_frequency": "none",
      "affected_departments": []
    },
    "hiring_signals": {
      "hiring_velocity": "moderate",
      "hiring_freeze_score": 0.1
    },
    "role_risk_map": {
      "sales": 0.1,
      "designer": 0.1,
      "hr_recruiter": 0.1,
      "data_scientist": 0.1,
      "product_manager": 0.1,
      "software_engineer": 0.1
    },
    "ai_exposure_index": 0.5,
    "market_risk_score": 0.15,
    "company_risk_score": 0.1,
    "confidence_score": 0.95,
    "archetype": "mature_stable",
    "data_source": "expansion_batch_2026_real",
    "last_updated": "2026-04-28"
  },
  {
    "company_name": "Brightstar Lottery PLC",
    "industry": "Gambling",
    "company_size": "enterprise",
    "stage": "public",
    "workforce_count": 5746,
    "open_jobs_count": 0,
    "financial_signals": {
      "burn_rate": "moderate",
      "funding_stage": "Public (NASDAQ/NYSE)",
      "revenue_trend": "stable",
      "months_since_last_funding": 120
    },
    "layoff_history": {
      "total_layoffs": 0,
      "last_layoff_date": "No History",
      "layoff_frequency": "none",
      "affected_departments": []
    },
    "hiring_signals": {
      "hiring_velocity": "moderate",
      "hiring_freeze_score": 0.1
    },
    "role_risk_map": {
      "sales": 0.1,
      "designer": 0.1,
      "hr_recruiter": 0.1,
      "data_scientist": 0.1,
      "product_manager": 0.1,
      "software_engineer": 0.1
    },
    "ai_exposure_index": 0.5,
    "market_risk_score": 0.15,
    "company_risk_score": 0.1,
    "confidence_score": 0.95,
    "archetype": "mature_stable",
    "data_source": "expansion_batch_2026_real",
    "last_updated": "2026-04-28"
  },
  {
    "company_name": "NETSCOUT SYSTEMS INC",
    "industry": "Software - Infrastructure",
    "company_size": "large",
    "stage": "public",
    "workforce_count": 2102,
    "open_jobs_count": 0,
    "financial_signals": {
      "burn_rate": "moderate",
      "funding_stage": "Public (NASDAQ/NYSE)",
      "revenue_trend": "stable",
      "months_since_last_funding": 120
    },
    "layoff_history": {
      "total_layoffs": 0,
      "last_layoff_date": "No History",
      "layoff_frequency": "none",
      "affected_departments": []
    },
    "hiring_signals": {
      "hiring_velocity": "moderate",
      "hiring_freeze_score": 0.1
    },
    "role_risk_map": {
      "sales": 0.1,
      "designer": 0.1,
      "hr_recruiter": 0.1,
      "data_scientist": 0.1,
      "product_manager": 0.1,
      "software_engineer": 0.1
    },
    "ai_exposure_index": 0.5,
    "market_risk_score": 0.15,
    "company_risk_score": 0.1,
    "confidence_score": 0.95,
    "archetype": "mature_stable",
    "data_source": "expansion_batch_2026_real",
    "last_updated": "2026-04-28"
  },
  {
    "company_name": "Eos Energy Enterprises, Inc.",
    "industry": "Electrical Equipment & Parts",
    "company_size": "mid",
    "stage": "public",
    "workforce_count": 787,
    "open_jobs_count": 0,
    "financial_signals": {
      "burn_rate": "moderate",
      "funding_stage": "Public (NASDAQ/NYSE)",
      "revenue_trend": "stable",
      "months_since_last_funding": 120
    },
    "layoff_history": {
      "total_layoffs": 0,
      "last_layoff_date": "No History",
      "layoff_frequency": "none",
      "affected_departments": []
    },
    "hiring_signals": {
      "hiring_velocity": "moderate",
      "hiring_freeze_score": 0.1
    },
    "role_risk_map": {
      "sales": 0.1,
      "designer": 0.1,
      "hr_recruiter": 0.1,
      "data_scientist": 0.1,
      "product_manager": 0.1,
      "software_engineer": 0.1
    },
    "ai_exposure_index": 0.5,
    "market_risk_score": 0.15,
    "company_risk_score": 0.1,
    "confidence_score": 0.95,
    "archetype": "mature_stable",
    "data_source": "expansion_batch_2026_real",
    "last_updated": "2026-04-28"
  },
  {
    "company_name": "Mineralys Therapeutics, Inc.",
    "industry": "Biotechnology",
    "company_size": "mid",
    "stage": "public",
    "workforce_count": 76,
    "open_jobs_count": 0,
    "financial_signals": {
      "burn_rate": "moderate",
      "funding_stage": "Public (NASDAQ/NYSE)",
      "revenue_trend": "stable",
      "months_since_last_funding": 120
    },
    "layoff_history": {
      "total_layoffs": 0,
      "last_layoff_date": "No History",
      "layoff_frequency": "none",
      "affected_departments": []
    },
    "hiring_signals": {
      "hiring_velocity": "moderate",
      "hiring_freeze_score": 0.1
    },
    "role_risk_map": {
      "sales": 0.1,
      "designer": 0.1,
      "hr_recruiter": 0.1,
      "data_scientist": 0.1,
      "product_manager": 0.1,
      "software_engineer": 0.1
    },
    "ai_exposure_index": 0.5,
    "market_risk_score": 0.15,
    "company_risk_score": 0.1,
    "confidence_score": 0.95,
    "archetype": "mature_stable",
    "data_source": "expansion_batch_2026_real",
    "last_updated": "2026-04-28"
  },
  {
    "company_name": "CECO ENVIRONMENTAL CORP",
    "industry": "Pollution & Treatment Controls",
    "company_size": "large",
    "stage": "public",
    "workforce_count": 1540,
    "open_jobs_count": 0,
    "financial_signals": {
      "burn_rate": "moderate",
      "funding_stage": "Public (NASDAQ/NYSE)",
      "revenue_trend": "stable",
      "months_since_last_funding": 120
    },
    "layoff_history": {
      "total_layoffs": 0,
      "last_layoff_date": "No History",
      "layoff_frequency": "none",
      "affected_departments": []
    },
    "hiring_signals": {
      "hiring_velocity": "moderate",
      "hiring_freeze_score": 0.1
    },
    "role_risk_map": {
      "sales": 0.1,
      "designer": 0.1,
      "hr_recruiter": 0.1,
      "data_scientist": 0.1,
      "product_manager": 0.1,
      "software_engineer": 0.1
    },
    "ai_exposure_index": 0.5,
    "market_risk_score": 0.15,
    "company_risk_score": 0.1,
    "confidence_score": 0.95,
    "archetype": "mature_stable",
    "data_source": "expansion_batch_2026_real",
    "last_updated": "2026-04-28"
  },
  {
    "company_name": "Tenable Holdings, Inc.",
    "industry": "Software - Infrastructure",
    "company_size": "large",
    "stage": "public",
    "workforce_count": 1995,
    "open_jobs_count": 0,
    "financial_signals": {
      "burn_rate": "moderate",
      "funding_stage": "Public (NASDAQ/NYSE)",
      "revenue_trend": "stable",
      "months_since_last_funding": 120
    },
    "layoff_history": {
      "total_layoffs": 0,
      "last_layoff_date": "No History",
      "layoff_frequency": "none",
      "affected_departments": []
    },
    "hiring_signals": {
      "hiring_velocity": "moderate",
      "hiring_freeze_score": 0.1
    },
    "role_risk_map": {
      "sales": 0.1,
      "designer": 0.1,
      "hr_recruiter": 0.1,
      "data_scientist": 0.1,
      "product_manager": 0.1,
      "software_engineer": 0.1
    },
    "ai_exposure_index": 0.5,
    "market_risk_score": 0.15,
    "company_risk_score": 0.1,
    "confidence_score": 0.95,
    "archetype": "mature_stable",
    "data_source": "expansion_batch_2026_real",
    "last_updated": "2026-04-28"
  },
  {
    "company_name": "Curaleaf Holdings, Inc.",
    "industry": "Drug Manufacturers - Specialty & Generic",
    "company_size": "enterprise",
    "stage": "public",
    "workforce_count": 5554,
    "open_jobs_count": 0,
    "financial_signals": {
      "burn_rate": "moderate",
      "funding_stage": "Public (NASDAQ/NYSE)",
      "revenue_trend": "stable",
      "months_since_last_funding": 120
    },
    "layoff_history": {
      "total_layoffs": 0,
      "last_layoff_date": "No History",
      "layoff_frequency": "none",
      "affected_departments": []
    },
    "hiring_signals": {
      "hiring_velocity": "moderate",
      "hiring_freeze_score": 0.1
    },
    "role_risk_map": {
      "sales": 0.1,
      "designer": 0.1,
      "hr_recruiter": 0.1,
      "data_scientist": 0.1,
      "product_manager": 0.1,
      "software_engineer": 0.1
    },
    "ai_exposure_index": 0.5,
    "market_risk_score": 0.15,
    "company_risk_score": 0.1,
    "confidence_score": 0.95,
    "archetype": "mature_stable",
    "data_source": "expansion_batch_2026_real",
    "last_updated": "2026-04-28"
  },
  {
    "company_name": "Definium Therapeutics, Inc.",
    "industry": "Biotechnology",
    "company_size": "mid",
    "stage": "public",
    "workforce_count": 105,
    "open_jobs_count": 0,
    "financial_signals": {
      "burn_rate": "moderate",
      "funding_stage": "Public (NASDAQ/NYSE)",
      "revenue_trend": "stable",
      "months_since_last_funding": 120
    },
    "layoff_history": {
      "total_layoffs": 0,
      "last_layoff_date": "No History",
      "layoff_frequency": "none",
      "affected_departments": []
    },
    "hiring_signals": {
      "hiring_velocity": "moderate",
      "hiring_freeze_score": 0.1
    },
    "role_risk_map": {
      "sales": 0.1,
      "designer": 0.1,
      "hr_recruiter": 0.1,
      "data_scientist": 0.1,
      "product_manager": 0.1,
      "software_engineer": 0.1
    },
    "ai_exposure_index": 0.5,
    "market_risk_score": 0.15,
    "company_risk_score": 0.1,
    "confidence_score": 0.95,
    "archetype": "mature_stable",
    "data_source": "expansion_batch_2026_real",
    "last_updated": "2026-04-28"
  },
  {
    "company_name": "DNOW Inc.",
    "industry": "Industrial Distribution",
    "company_size": "large",
    "stage": "public",
    "workforce_count": 4945,
    "open_jobs_count": 0,
    "financial_signals": {
      "burn_rate": "moderate",
      "funding_stage": "Public (NASDAQ/NYSE)",
      "revenue_trend": "stable",
      "months_since_last_funding": 120
    },
    "layoff_history": {
      "total_layoffs": 0,
      "last_layoff_date": "No History",
      "layoff_frequency": "none",
      "affected_departments": []
    },
    "hiring_signals": {
      "hiring_velocity": "moderate",
      "hiring_freeze_score": 0.1
    },
    "role_risk_map": {
      "sales": 0.1,
      "designer": 0.1,
      "hr_recruiter": 0.1,
      "data_scientist": 0.1,
      "product_manager": 0.1,
      "software_engineer": 0.1
    },
    "ai_exposure_index": 0.5,
    "market_risk_score": 0.15,
    "company_risk_score": 0.1,
    "confidence_score": 0.95,
    "archetype": "mature_stable",
    "data_source": "expansion_batch_2026_real",
    "last_updated": "2026-04-28"
  },
  {
    "company_name": "PENN Entertainment, Inc.",
    "industry": "Resorts & Casinos",
    "company_size": "global_giant",
    "stage": "public",
    "workforce_count": 23441,
    "open_jobs_count": 0,
    "financial_signals": {
      "burn_rate": "moderate",
      "funding_stage": "Public (NASDAQ/NYSE)",
      "revenue_trend": "stable",
      "months_since_last_funding": 120
    },
    "layoff_history": {
      "total_layoffs": 0,
      "last_layoff_date": "No History",
      "layoff_frequency": "none",
      "affected_departments": []
    },
    "hiring_signals": {
      "hiring_velocity": "moderate",
      "hiring_freeze_score": 0.1
    },
    "role_risk_map": {
      "sales": 0.1,
      "designer": 0.1,
      "hr_recruiter": 0.1,
      "data_scientist": 0.1,
      "product_manager": 0.1,
      "software_engineer": 0.1
    },
    "ai_exposure_index": 0.5,
    "market_risk_score": 0.15,
    "company_risk_score": 0.1,
    "confidence_score": 0.95,
    "archetype": "mature_stable",
    "data_source": "expansion_batch_2026_real",
    "last_updated": "2026-04-28"
  },
  {
    "company_name": "Freshworks Inc.",
    "industry": "Software - Application",
    "company_size": "large",
    "stage": "public",
    "workforce_count": 4500,
    "open_jobs_count": 0,
    "financial_signals": {
      "burn_rate": "moderate",
      "funding_stage": "Public (NASDAQ/NYSE)",
      "revenue_trend": "stable",
      "months_since_last_funding": 120
    },
    "layoff_history": {
      "total_layoffs": 0,
      "last_layoff_date": "No History",
      "layoff_frequency": "none",
      "affected_departments": []
    },
    "hiring_signals": {
      "hiring_velocity": "moderate",
      "hiring_freeze_score": 0.1
    },
    "role_risk_map": {
      "sales": 0.1,
      "designer": 0.1,
      "hr_recruiter": 0.1,
      "data_scientist": 0.1,
      "product_manager": 0.1,
      "software_engineer": 0.1
    },
    "ai_exposure_index": 0.5,
    "market_risk_score": 0.15,
    "company_risk_score": 0.1,
    "confidence_score": 0.95,
    "archetype": "mature_stable",
    "data_source": "expansion_batch_2026_real",
    "last_updated": "2026-04-28"
  },
  {
    "company_name": "Mister Car Wash, Inc.",
    "industry": "Auto & Truck Dealerships",
    "company_size": "enterprise",
    "stage": "public",
    "workforce_count": 6836,
    "open_jobs_count": 0,
    "financial_signals": {
      "burn_rate": "moderate",
      "funding_stage": "Public (NASDAQ/NYSE)",
      "revenue_trend": "stable",
      "months_since_last_funding": 120
    },
    "layoff_history": {
      "total_layoffs": 0,
      "last_layoff_date": "No History",
      "layoff_frequency": "none",
      "affected_departments": []
    },
    "hiring_signals": {
      "hiring_velocity": "moderate",
      "hiring_freeze_score": 0.1
    },
    "role_risk_map": {
      "sales": 0.1,
      "designer": 0.1,
      "hr_recruiter": 0.1,
      "data_scientist": 0.1,
      "product_manager": 0.1,
      "software_engineer": 0.1
    },
    "ai_exposure_index": 0.5,
    "market_risk_score": 0.15,
    "company_risk_score": 0.1,
    "confidence_score": 0.95,
    "archetype": "mature_stable",
    "data_source": "expansion_batch_2026_real",
    "last_updated": "2026-04-28"
  },
  {
    "company_name": "Melco Resorts & Entertainment LTD",
    "industry": "Resorts & Casinos",
    "company_size": "global_giant",
    "stage": "public",
    "workforce_count": 22961,
    "open_jobs_count": 0,
    "financial_signals": {
      "burn_rate": "moderate",
      "funding_stage": "Public (NASDAQ/NYSE)",
      "revenue_trend": "stable",
      "months_since_last_funding": 120
    },
    "layoff_history": {
      "total_layoffs": 0,
      "last_layoff_date": "No History",
      "layoff_frequency": "none",
      "affected_departments": []
    },
    "hiring_signals": {
      "hiring_velocity": "moderate",
      "hiring_freeze_score": 0.1
    },
    "role_risk_map": {
      "sales": 0.1,
      "designer": 0.1,
      "hr_recruiter": 0.1,
      "data_scientist": 0.1,
      "product_manager": 0.1,
      "software_engineer": 0.1
    },
    "ai_exposure_index": 0.5,
    "market_risk_score": 0.15,
    "company_risk_score": 0.1,
    "confidence_score": 0.95,
    "archetype": "mature_stable",
    "data_source": "expansion_batch_2026_real",
    "last_updated": "2026-04-28"
  },
  {
    "company_name": "BANNER CORP",
    "industry": "Banks - Regional",
    "company_size": "large",
    "stage": "public",
    "workforce_count": 1916,
    "open_jobs_count": 0,
    "financial_signals": {
      "burn_rate": "moderate",
      "funding_stage": "Public (NASDAQ/NYSE)",
      "revenue_trend": "stable",
      "months_since_last_funding": 120
    },
    "layoff_history": {
      "total_layoffs": 0,
      "last_layoff_date": "No History",
      "layoff_frequency": "none",
      "affected_departments": []
    },
    "hiring_signals": {
      "hiring_velocity": "moderate",
      "hiring_freeze_score": 0.1
    },
    "role_risk_map": {
      "sales": 0.1,
      "designer": 0.1,
      "hr_recruiter": 0.1,
      "data_scientist": 0.1,
      "product_manager": 0.1,
      "software_engineer": 0.1
    },
    "ai_exposure_index": 0.5,
    "market_risk_score": 0.15,
    "company_risk_score": 0.1,
    "confidence_score": 0.95,
    "archetype": "mature_stable",
    "data_source": "expansion_batch_2026_real",
    "last_updated": "2026-04-28"
  },
  {
    "company_name": "PITNEY BOWES INC /DE/",
    "industry": "Integrated Freight & Logistics",
    "company_size": "enterprise",
    "stage": "public",
    "workforce_count": 6600,
    "open_jobs_count": 0,
    "financial_signals": {
      "burn_rate": "moderate",
      "funding_stage": "Public (NASDAQ/NYSE)",
      "revenue_trend": "stable",
      "months_since_last_funding": 120
    },
    "layoff_history": {
      "total_layoffs": 0,
      "last_layoff_date": "No History",
      "layoff_frequency": "none",
      "affected_departments": []
    },
    "hiring_signals": {
      "hiring_velocity": "moderate",
      "hiring_freeze_score": 0.1
    },
    "role_risk_map": {
      "sales": 0.1,
      "designer": 0.1,
      "hr_recruiter": 0.1,
      "data_scientist": 0.1,
      "product_manager": 0.1,
      "software_engineer": 0.1
    },
    "ai_exposure_index": 0.5,
    "market_risk_score": 0.15,
    "company_risk_score": 0.1,
    "confidence_score": 0.95,
    "archetype": "mature_stable",
    "data_source": "expansion_batch_2026_real",
    "last_updated": "2026-04-28"
  },
  {
    "company_name": "Lucid Group, Inc.",
    "industry": "Auto Manufacturers",
    "company_size": "enterprise",
    "stage": "public",
    "workforce_count": 9000,
    "open_jobs_count": 0,
    "financial_signals": {
      "burn_rate": "moderate",
      "funding_stage": "Public (NASDAQ/NYSE)",
      "revenue_trend": "stable",
      "months_since_last_funding": 120
    },
    "layoff_history": {
      "total_layoffs": 0,
      "last_layoff_date": "No History",
      "layoff_frequency": "none",
      "affected_departments": []
    },
    "hiring_signals": {
      "hiring_velocity": "moderate",
      "hiring_freeze_score": 0.1
    },
    "role_risk_map": {
      "sales": 0.1,
      "designer": 0.1,
      "hr_recruiter": 0.1,
      "data_scientist": 0.1,
      "product_manager": 0.1,
      "software_engineer": 0.1
    },
    "ai_exposure_index": 0.5,
    "market_risk_score": 0.15,
    "company_risk_score": 0.1,
    "confidence_score": 0.95,
    "archetype": "mature_stable",
    "data_source": "expansion_batch_2026_real",
    "last_updated": "2026-04-28"
  },
  {
    "company_name": "VERRA MOBILITY Corp",
    "industry": "Information Technology Services",
    "company_size": "large",
    "stage": "public",
    "workforce_count": 1888,
    "open_jobs_count": 0,
    "financial_signals": {
      "burn_rate": "moderate",
      "funding_stage": "Public (NASDAQ/NYSE)",
      "revenue_trend": "stable",
      "months_since_last_funding": 120
    },
    "layoff_history": {
      "total_layoffs": 0,
      "last_layoff_date": "No History",
      "layoff_frequency": "none",
      "affected_departments": []
    },
    "hiring_signals": {
      "hiring_velocity": "moderate",
      "hiring_freeze_score": 0.1
    },
    "role_risk_map": {
      "sales": 0.1,
      "designer": 0.1,
      "hr_recruiter": 0.1,
      "data_scientist": 0.1,
      "product_manager": 0.1,
      "software_engineer": 0.1
    },
    "ai_exposure_index": 0.5,
    "market_risk_score": 0.15,
    "company_risk_score": 0.1,
    "confidence_score": 0.95,
    "archetype": "mature_stable",
    "data_source": "expansion_batch_2026_real",
    "last_updated": "2026-04-28"
  },
  {
    "company_name": "CSG SYSTEMS INTERNATIONAL INC",
    "industry": "Software - Infrastructure",
    "company_size": "enterprise",
    "stage": "public",
    "workforce_count": 5500,
    "open_jobs_count": 0,
    "financial_signals": {
      "burn_rate": "moderate",
      "funding_stage": "Public (NASDAQ/NYSE)",
      "revenue_trend": "stable",
      "months_since_last_funding": 120
    },
    "layoff_history": {
      "total_layoffs": 0,
      "last_layoff_date": "No History",
      "layoff_frequency": "none",
      "affected_departments": []
    },
    "hiring_signals": {
      "hiring_velocity": "moderate",
      "hiring_freeze_score": 0.1
    },
    "role_risk_map": {
      "sales": 0.1,
      "designer": 0.1,
      "hr_recruiter": 0.1,
      "data_scientist": 0.1,
      "product_manager": 0.1,
      "software_engineer": 0.1
    },
    "ai_exposure_index": 0.5,
    "market_risk_score": 0.15,
    "company_risk_score": 0.1,
    "confidence_score": 0.95,
    "archetype": "mature_stable",
    "data_source": "expansion_batch_2026_real",
    "last_updated": "2026-04-28"
  },
  {
    "company_name": "ROGERS CORP",
    "industry": "Electronic Components",
    "company_size": "large",
    "stage": "public",
    "workforce_count": 3000,
    "open_jobs_count": 0,
    "financial_signals": {
      "burn_rate": "moderate",
      "funding_stage": "Public (NASDAQ/NYSE)",
      "revenue_trend": "stable",
      "months_since_last_funding": 120
    },
    "layoff_history": {
      "total_layoffs": 0,
      "last_layoff_date": "No History",
      "layoff_frequency": "none",
      "affected_departments": []
    },
    "hiring_signals": {
      "hiring_velocity": "moderate",
      "hiring_freeze_score": 0.1
    },
    "role_risk_map": {
      "sales": 0.1,
      "designer": 0.1,
      "hr_recruiter": 0.1,
      "data_scientist": 0.1,
      "product_manager": 0.1,
      "software_engineer": 0.1
    },
    "ai_exposure_index": 0.5,
    "market_risk_score": 0.15,
    "company_risk_score": 0.1,
    "confidence_score": 0.95,
    "archetype": "mature_stable",
    "data_source": "expansion_batch_2026_real",
    "last_updated": "2026-04-28"
  },
  {
    "company_name": "Merchants Bancorp",
    "industry": "Banks - Regional",
    "company_size": "mid",
    "stage": "public",
    "workforce_count": 735,
    "open_jobs_count": 0,
    "financial_signals": {
      "burn_rate": "moderate",
      "funding_stage": "Public (NASDAQ/NYSE)",
      "revenue_trend": "stable",
      "months_since_last_funding": 120
    },
    "layoff_history": {
      "total_layoffs": 0,
      "last_layoff_date": "No History",
      "layoff_frequency": "none",
      "affected_departments": []
    },
    "hiring_signals": {
      "hiring_velocity": "moderate",
      "hiring_freeze_score": 0.1
    },
    "role_risk_map": {
      "sales": 0.1,
      "designer": 0.1,
      "hr_recruiter": 0.1,
      "data_scientist": 0.1,
      "product_manager": 0.1,
      "software_engineer": 0.1
    },
    "ai_exposure_index": 0.5,
    "market_risk_score": 0.15,
    "company_risk_score": 0.1,
    "confidence_score": 0.95,
    "archetype": "mature_stable",
    "data_source": "expansion_batch_2026_real",
    "last_updated": "2026-04-28"
  },
  {
    "company_name": "EXTREME NETWORKS INC",
    "industry": "Communication Equipment",
    "company_size": "large",
    "stage": "public",
    "workforce_count": 2811,
    "open_jobs_count": 0,
    "financial_signals": {
      "burn_rate": "moderate",
      "funding_stage": "Public (NASDAQ/NYSE)",
      "revenue_trend": "stable",
      "months_since_last_funding": 120
    },
    "layoff_history": {
      "total_layoffs": 0,
      "last_layoff_date": "No History",
      "layoff_frequency": "none",
      "affected_departments": []
    },
    "hiring_signals": {
      "hiring_velocity": "moderate",
      "hiring_freeze_score": 0.1
    },
    "role_risk_map": {
      "sales": 0.1,
      "designer": 0.1,
      "hr_recruiter": 0.1,
      "data_scientist": 0.1,
      "product_manager": 0.1,
      "software_engineer": 0.1
    },
    "ai_exposure_index": 0.5,
    "market_risk_score": 0.15,
    "company_risk_score": 0.1,
    "confidence_score": 0.95,
    "archetype": "mature_stable",
    "data_source": "expansion_batch_2026_real",
    "last_updated": "2026-04-28"
  },
  {
    "company_name": "Slide Insurance Holdings, Inc.",
    "industry": "Insurance - Property & Casualty",
    "company_size": "mid",
    "stage": "public",
    "workforce_count": 504,
    "open_jobs_count": 0,
    "financial_signals": {
      "burn_rate": "moderate",
      "funding_stage": "Public (NASDAQ/NYSE)",
      "revenue_trend": "stable",
      "months_since_last_funding": 120
    },
    "layoff_history": {
      "total_layoffs": 0,
      "last_layoff_date": "No History",
      "layoff_frequency": "none",
      "affected_departments": []
    },
    "hiring_signals": {
      "hiring_velocity": "moderate",
      "hiring_freeze_score": 0.1
    },
    "role_risk_map": {
      "sales": 0.1,
      "designer": 0.1,
      "hr_recruiter": 0.1,
      "data_scientist": 0.1,
      "product_manager": 0.1,
      "software_engineer": 0.1
    },
    "ai_exposure_index": 0.5,
    "market_risk_score": 0.15,
    "company_risk_score": 0.1,
    "confidence_score": 0.95,
    "archetype": "mature_stable",
    "data_source": "expansion_batch_2026_real",
    "last_updated": "2026-04-28"
  },
  {
    "company_name": "FIRST BUSEY CORP /NV/",
    "industry": "Banks - Regional",
    "company_size": "large",
    "stage": "public",
    "workforce_count": 1880,
    "open_jobs_count": 0,
    "financial_signals": {
      "burn_rate": "moderate",
      "funding_stage": "Public (NASDAQ/NYSE)",
      "revenue_trend": "stable",
      "months_since_last_funding": 120
    },
    "layoff_history": {
      "total_layoffs": 0,
      "last_layoff_date": "No History",
      "layoff_frequency": "none",
      "affected_departments": []
    },
    "hiring_signals": {
      "hiring_velocity": "moderate",
      "hiring_freeze_score": 0.1
    },
    "role_risk_map": {
      "sales": 0.1,
      "designer": 0.1,
      "hr_recruiter": 0.1,
      "data_scientist": 0.1,
      "product_manager": 0.1,
      "software_engineer": 0.1
    },
    "ai_exposure_index": 0.5,
    "market_risk_score": 0.15,
    "company_risk_score": 0.1,
    "confidence_score": 0.95,
    "archetype": "mature_stable",
    "data_source": "expansion_batch_2026_real",
    "last_updated": "2026-04-28"
  },
  {
    "company_name": "HELIOS TECHNOLOGIES, INC.",
    "industry": "Specialty Industrial Machinery",
    "company_size": "large",
    "stage": "public",
    "workforce_count": 2300,
    "open_jobs_count": 0,
    "financial_signals": {
      "burn_rate": "moderate",
      "funding_stage": "Public (NASDAQ/NYSE)",
      "revenue_trend": "stable",
      "months_since_last_funding": 120
    },
    "layoff_history": {
      "total_layoffs": 0,
      "last_layoff_date": "No History",
      "layoff_frequency": "none",
      "affected_departments": []
    },
    "hiring_signals": {
      "hiring_velocity": "moderate",
      "hiring_freeze_score": 0.1
    },
    "role_risk_map": {
      "sales": 0.1,
      "designer": 0.1,
      "hr_recruiter": 0.1,
      "data_scientist": 0.1,
      "product_manager": 0.1,
      "software_engineer": 0.1
    },
    "ai_exposure_index": 0.5,
    "market_risk_score": 0.15,
    "company_risk_score": 0.1,
    "confidence_score": 0.95,
    "archetype": "mature_stable",
    "data_source": "expansion_batch_2026_real",
    "last_updated": "2026-04-28"
  },
  {
    "company_name": "Hilltop Holdings Inc.",
    "industry": "Financial Conglomerates",
    "company_size": "large",
    "stage": "public",
    "workforce_count": 3520,
    "open_jobs_count": 0,
    "financial_signals": {
      "burn_rate": "moderate",
      "funding_stage": "Public (NASDAQ/NYSE)",
      "revenue_trend": "stable",
      "months_since_last_funding": 120
    },
    "layoff_history": {
      "total_layoffs": 0,
      "last_layoff_date": "No History",
      "layoff_frequency": "none",
      "affected_departments": []
    },
    "hiring_signals": {
      "hiring_velocity": "moderate",
      "hiring_freeze_score": 0.1
    },
    "role_risk_map": {
      "sales": 0.1,
      "designer": 0.1,
      "hr_recruiter": 0.1,
      "data_scientist": 0.1,
      "product_manager": 0.1,
      "software_engineer": 0.1
    },
    "ai_exposure_index": 0.5,
    "market_risk_score": 0.15,
    "company_risk_score": 0.1,
    "confidence_score": 0.95,
    "archetype": "mature_stable",
    "data_source": "expansion_batch_2026_real",
    "last_updated": "2026-04-28"
  },
  {
    "company_name": "Northwest Natural Holding Co",
    "industry": "Utilities - Regulated Gas",
    "company_size": "large",
    "stage": "public",
    "workforce_count": 1619,
    "open_jobs_count": 0,
    "financial_signals": {
      "burn_rate": "moderate",
      "funding_stage": "Public (NASDAQ/NYSE)",
      "revenue_trend": "stable",
      "months_since_last_funding": 120
    },
    "layoff_history": {
      "total_layoffs": 0,
      "last_layoff_date": "No History",
      "layoff_frequency": "none",
      "affected_departments": []
    },
    "hiring_signals": {
      "hiring_velocity": "moderate",
      "hiring_freeze_score": 0.1
    },
    "role_risk_map": {
      "sales": 0.1,
      "designer": 0.1,
      "hr_recruiter": 0.1,
      "data_scientist": 0.1,
      "product_manager": 0.1,
      "software_engineer": 0.1
    },
    "ai_exposure_index": 0.5,
    "market_risk_score": 0.15,
    "company_risk_score": 0.1,
    "confidence_score": 0.95,
    "archetype": "mature_stable",
    "data_source": "expansion_batch_2026_real",
    "last_updated": "2026-04-28"
  },
  {
    "company_name": "ANADOLU EFES BIRACILIK VE MALT SANAYI A S/ADR",
    "industry": "Beverages - Non-Alcoholic",
    "company_size": "global_giant",
    "stage": "public",
    "workforce_count": 15318,
    "open_jobs_count": 0,
    "financial_signals": {
      "burn_rate": "moderate",
      "funding_stage": "Public (NASDAQ/NYSE)",
      "revenue_trend": "stable",
      "months_since_last_funding": 120
    },
    "layoff_history": {
      "total_layoffs": 0,
      "last_layoff_date": "No History",
      "layoff_frequency": "none",
      "affected_departments": []
    },
    "hiring_signals": {
      "hiring_velocity": "moderate",
      "hiring_freeze_score": 0.1
    },
    "role_risk_map": {
      "sales": 0.1,
      "designer": 0.1,
      "hr_recruiter": 0.1,
      "data_scientist": 0.1,
      "product_manager": 0.1,
      "software_engineer": 0.1
    },
    "ai_exposure_index": 0.5,
    "market_risk_score": 0.15,
    "company_risk_score": 0.1,
    "confidence_score": 0.95,
    "archetype": "mature_stable",
    "data_source": "expansion_batch_2026_real",
    "last_updated": "2026-04-28"
  },
  {
    "company_name": "Bank of N.T. Butterfield & Son Ltd",
    "industry": "Banks - Diversified",
    "company_size": "large",
    "stage": "public",
    "workforce_count": 1299,
    "open_jobs_count": 0,
    "financial_signals": {
      "burn_rate": "moderate",
      "funding_stage": "Public (NASDAQ/NYSE)",
      "revenue_trend": "stable",
      "months_since_last_funding": 120
    },
    "layoff_history": {
      "total_layoffs": 0,
      "last_layoff_date": "No History",
      "layoff_frequency": "none",
      "affected_departments": []
    },
    "hiring_signals": {
      "hiring_velocity": "moderate",
      "hiring_freeze_score": 0.1
    },
    "role_risk_map": {
      "sales": 0.1,
      "designer": 0.1,
      "hr_recruiter": 0.1,
      "data_scientist": 0.1,
      "product_manager": 0.1,
      "software_engineer": 0.1
    },
    "ai_exposure_index": 0.5,
    "market_risk_score": 0.15,
    "company_risk_score": 0.1,
    "confidence_score": 0.95,
    "archetype": "mature_stable",
    "data_source": "expansion_batch_2026_real",
    "last_updated": "2026-04-28"
  },
  {
    "company_name": "Sigma Lithium Corp",
    "industry": "Other Industrial Metals & Mining",
    "company_size": "mid",
    "stage": "public",
    "workforce_count": 560,
    "open_jobs_count": 0,
    "financial_signals": {
      "burn_rate": "moderate",
      "funding_stage": "Public (NASDAQ/NYSE)",
      "revenue_trend": "stable",
      "months_since_last_funding": 120
    },
    "layoff_history": {
      "total_layoffs": 0,
      "last_layoff_date": "No History",
      "layoff_frequency": "none",
      "affected_departments": []
    },
    "hiring_signals": {
      "hiring_velocity": "moderate",
      "hiring_freeze_score": 0.1
    },
    "role_risk_map": {
      "sales": 0.1,
      "designer": 0.1,
      "hr_recruiter": 0.1,
      "data_scientist": 0.1,
      "product_manager": 0.1,
      "software_engineer": 0.1
    },
    "ai_exposure_index": 0.5,
    "market_risk_score": 0.15,
    "company_risk_score": 0.1,
    "confidence_score": 0.95,
    "archetype": "mature_stable",
    "data_source": "expansion_batch_2026_real",
    "last_updated": "2026-04-28"
  },
  {
    "company_name": "EPLUS INC",
    "industry": "Software - Application",
    "company_size": "large",
    "stage": "public",
    "workforce_count": 2199,
    "open_jobs_count": 0,
    "financial_signals": {
      "burn_rate": "moderate",
      "funding_stage": "Public (NASDAQ/NYSE)",
      "revenue_trend": "stable",
      "months_since_last_funding": 120
    },
    "layoff_history": {
      "total_layoffs": 0,
      "last_layoff_date": "No History",
      "layoff_frequency": "none",
      "affected_departments": []
    },
    "hiring_signals": {
      "hiring_velocity": "moderate",
      "hiring_freeze_score": 0.1
    },
    "role_risk_map": {
      "sales": 0.1,
      "designer": 0.1,
      "hr_recruiter": 0.1,
      "data_scientist": 0.1,
      "product_manager": 0.1,
      "software_engineer": 0.1
    },
    "ai_exposure_index": 0.5,
    "market_risk_score": 0.15,
    "company_risk_score": 0.1,
    "confidence_score": 0.95,
    "archetype": "mature_stable",
    "data_source": "expansion_batch_2026_real",
    "last_updated": "2026-04-28"
  },
  {
    "company_name": "Organon & Co.",
    "industry": "Drug Manufacturers - General",
    "company_size": "enterprise",
    "stage": "public",
    "workforce_count": 10000,
    "open_jobs_count": 0,
    "financial_signals": {
      "burn_rate": "moderate",
      "funding_stage": "Public (NASDAQ/NYSE)",
      "revenue_trend": "stable",
      "months_since_last_funding": 120
    },
    "layoff_history": {
      "total_layoffs": 0,
      "last_layoff_date": "No History",
      "layoff_frequency": "none",
      "affected_departments": []
    },
    "hiring_signals": {
      "hiring_velocity": "moderate",
      "hiring_freeze_score": 0.1
    },
    "role_risk_map": {
      "sales": 0.1,
      "designer": 0.1,
      "hr_recruiter": 0.1,
      "data_scientist": 0.1,
      "product_manager": 0.1,
      "software_engineer": 0.1
    },
    "ai_exposure_index": 0.5,
    "market_risk_score": 0.15,
    "company_risk_score": 0.1,
    "confidence_score": 0.95,
    "archetype": "mature_stable",
    "data_source": "expansion_batch_2026_real",
    "last_updated": "2026-04-28"
  }
]