[
  {
    "company_name": "Everpure, Inc.",
    "industry": "Computer Hardware",
    "company_size": "enterprise",
    "stage": "public",
    "workforce_count": 6400,
    "open_jobs_count": 0,
    "financial_signals": {
      "burn_rate": "moderate",
      "funding_stage": "Public (NASDAQ/NYSE)",
      "revenue_trend": "stable",
      "months_since_last_funding": 120
    },
    "layoff_history": {
      "total_layoffs": 0,
      "last_layoff_date": "No History",
      "layoff_frequency": "none",
      "affected_departments": []
    },
    "hiring_signals": {
      "hiring_velocity": "moderate",
      "hiring_freeze_score": 0.1
    },
    "role_risk_map": {
      "sales": 0.1,
      "designer": 0.1,
      "hr_recruiter": 0.1,
      "data_scientist": 0.1,
      "product_manager": 0.1,
      "software_engineer": 0.1
    },
    "ai_exposure_index": 0.5,
    "market_risk_score": 0.15,
    "company_risk_score": 0.1,
    "confidence_score": 0.95,
    "archetype": "mature_stable",
    "data_source": "expansion_batch_2026_real",
    "last_updated": "2026-04-28"
  },
  {
    "company_name": "NISOURCE INC.",
    "industry": "Utilities - Regulated Gas",
    "company_size": "enterprise",
    "stage": "public",
    "workforce_count": 7668,
    "open_jobs_count": 0,
    "financial_signals": {
      "burn_rate": "moderate",
      "funding_stage": "Public (NASDAQ/NYSE)",
      "revenue_trend": "stable",
      "months_since_last_funding": 120
    },
    "layoff_history": {
      "total_layoffs": 0,
      "last_layoff_date": "No History",
      "layoff_frequency": "none",
      "affected_departments": []
    },
    "hiring_signals": {
      "hiring_velocity": "moderate",
      "hiring_freeze_score": 0.1
    },
    "role_risk_map": {
      "sales": 0.1,
      "designer": 0.1,
      "hr_recruiter": 0.1,
      "data_scientist": 0.1,
      "product_manager": 0.1,
      "software_engineer": 0.1
    },
    "ai_exposure_index": 0.5,
    "market_risk_score": 0.15,
    "company_risk_score": 0.1,
    "confidence_score": 0.95,
    "archetype": "mature_stable",
    "data_source": "expansion_batch_2026_real",
    "last_updated": "2026-04-28"
  },
  {
    "company_name": "nVent Electric plc",
    "industry": "Electrical Equipment & Parts",
    "company_size": "global_giant",
    "stage": "public",
    "workforce_count": 12000,
    "open_jobs_count": 0,
    "financial_signals": {
      "burn_rate": "moderate",
      "funding_stage": "Public (NASDAQ/NYSE)",
      "revenue_trend": "stable",
      "months_since_last_funding": 120
    },
    "layoff_history": {
      "total_layoffs": 0,
      "last_layoff_date": "No History",
      "layoff_frequency": "none",
      "affected_departments": []
    },
    "hiring_signals": {
      "hiring_velocity": "moderate",
      "hiring_freeze_score": 0.1
    },
    "role_risk_map": {
      "sales": 0.1,
      "designer": 0.1,
      "hr_recruiter": 0.1,
      "data_scientist": 0.1,
      "product_manager": 0.1,
      "software_engineer": 0.1
    },
    "ai_exposure_index": 0.5,
    "market_risk_score": 0.15,
    "company_risk_score": 0.1,
    "confidence_score": 0.95,
    "archetype": "mature_stable",
    "data_source": "expansion_batch_2026_real",
    "last_updated": "2026-04-28"
  },
  {
    "company_name": "AST SpaceMobile, Inc.",
    "industry": "Communication Equipment",
    "company_size": "large",
    "stage": "public",
    "workforce_count": 1126,
    "open_jobs_count": 0,
    "financial_signals": {
      "burn_rate": "moderate",
      "funding_stage": "Public (NASDAQ/NYSE)",
      "revenue_trend": "stable",
      "months_since_last_funding": 120
    },
    "layoff_history": {
      "total_layoffs": 0,
      "last_layoff_date": "No History",
      "layoff_frequency": "none",
      "affected_departments": []
    },
    "hiring_signals": {
      "hiring_velocity": "moderate",
      "hiring_freeze_score": 0.1
    },
    "role_risk_map": {
      "sales": 0.1,
      "designer": 0.1,
      "hr_recruiter": 0.1,
      "data_scientist": 0.1,
      "product_manager": 0.1,
      "software_engineer": 0.1
    },
    "ai_exposure_index": 0.5,
    "market_risk_score": 0.15,
    "company_risk_score": 0.1,
    "confidence_score": 0.95,
    "archetype": "mature_stable",
    "data_source": "expansion_batch_2026_real",
    "last_updated": "2026-04-28"
  },
  {
    "company_name": "BROWN & BROWN, INC.",
    "industry": "Insurance Brokers",
    "company_size": "global_giant",
    "stage": "public",
    "workforce_count": 22888,
    "open_jobs_count": 0,
    "financial_signals": {
      "burn_rate": "moderate",
      "funding_stage": "Public (NASDAQ/NYSE)",
      "revenue_trend": "stable",
      "months_since_last_funding": 120
    },
    "layoff_history": {
      "total_layoffs": 0,
      "last_layoff_date": "No History",
      "layoff_frequency": "none",
      "affected_departments": []
    },
    "hiring_signals": {
      "hiring_velocity": "moderate",
      "hiring_freeze_score": 0.1
    },
    "role_risk_map": {
      "sales": 0.1,
      "designer": 0.1,
      "hr_recruiter": 0.1,
      "data_scientist": 0.1,
      "product_manager": 0.1,
      "software_engineer": 0.1
    },
    "ai_exposure_index": 0.5,
    "market_risk_score": 0.15,
    "company_risk_score": 0.1,
    "confidence_score": 0.95,
    "archetype": "mature_stable",
    "data_source": "expansion_batch_2026_real",
    "last_updated": "2026-04-28"
  },
  {
    "company_name": "TYSON FOODS, INC.",
    "industry": "Farm Products",
    "company_size": "global_giant",
    "stage": "public",
    "workforce_count": 133000,
    "open_jobs_count": 0,
    "financial_signals": {
      "burn_rate": "moderate",
      "funding_stage": "Public (NASDAQ/NYSE)",
      "revenue_trend": "stable",
      "months_since_last_funding": 120
    },
    "layoff_history": {
      "total_layoffs": 0,
      "last_layoff_date": "No History",
      "layoff_frequency": "none",
      "affected_departments": []
    },
    "hiring_signals": {
      "hiring_velocity": "moderate",
      "hiring_freeze_score": 0.1
    },
    "role_risk_map": {
      "sales": 0.1,
      "designer": 0.1,
      "hr_recruiter": 0.1,
      "data_scientist": 0.1,
      "product_manager": 0.1,
      "software_engineer": 0.1
    },
    "ai_exposure_index": 0.5,
    "market_risk_score": 0.15,
    "company_risk_score": 0.1,
    "confidence_score": 0.95,
    "archetype": "mature_stable",
    "data_source": "expansion_batch_2026_real",
    "last_updated": "2026-04-28"
  },
  {
    "company_name": "WILLIAMS SONOMA INC",
    "industry": "Specialty Retail",
    "company_size": "global_giant",
    "stage": "public",
    "workforce_count": 19800,
    "open_jobs_count": 0,
    "financial_signals": {
      "burn_rate": "moderate",
      "funding_stage": "Public (NASDAQ/NYSE)",
      "revenue_trend": "stable",
      "months_since_last_funding": 120
    },
    "layoff_history": {
      "total_layoffs": 0,
      "last_layoff_date": "No History",
      "layoff_frequency": "none",
      "affected_departments": []
    },
    "hiring_signals": {
      "hiring_velocity": "moderate",
      "hiring_freeze_score": 0.1
    },
    "role_risk_map": {
      "sales": 0.1,
      "designer": 0.1,
      "hr_recruiter": 0.1,
      "data_scientist": 0.1,
      "product_manager": 0.1,
      "software_engineer": 0.1
    },
    "ai_exposure_index": 0.5,
    "market_risk_score": 0.15,
    "company_risk_score": 0.1,
    "confidence_score": 0.95,
    "archetype": "mature_stable",
    "data_source": "expansion_batch_2026_real",
    "last_updated": "2026-04-28"
  },
  {
    "company_name": "LyondellBasell Industries N.V.",
    "industry": "Specialty Chemicals",
    "company_size": "global_giant",
    "stage": "public",
    "workforce_count": 18970,
    "open_jobs_count": 0,
    "financial_signals": {
      "burn_rate": "moderate",
      "funding_stage": "Public (NASDAQ/NYSE)",
      "revenue_trend": "stable",
      "months_since_last_funding": 120
    },
    "layoff_history": {
      "total_layoffs": 0,
      "last_layoff_date": "No History",
      "layoff_frequency": "none",
      "affected_departments": []
    },
    "hiring_signals": {
      "hiring_velocity": "moderate",
      "hiring_freeze_score": 0.1
    },
    "role_risk_map": {
      "sales": 0.1,
      "designer": 0.1,
      "hr_recruiter": 0.1,
      "data_scientist": 0.1,
      "product_manager": 0.1,
      "software_engineer": 0.1
    },
    "ai_exposure_index": 0.5,
    "market_risk_score": 0.15,
    "company_risk_score": 0.1,
    "confidence_score": 0.95,
    "archetype": "mature_stable",
    "data_source": "expansion_batch_2026_real",
    "last_updated": "2026-04-28"
  },
  {
    "company_name": "ENTEGRIS INC",
    "industry": "Semiconductor Equipment & Materials",
    "company_size": "enterprise",
    "stage": "public",
    "workforce_count": 7700,
    "open_jobs_count": 0,
    "financial_signals": {
      "burn_rate": "moderate",
      "funding_stage": "Public (NASDAQ/NYSE)",
      "revenue_trend": "stable",
      "months_since_last_funding": 120
    },
    "layoff_history": {
      "total_layoffs": 0,
      "last_layoff_date": "No History",
      "layoff_frequency": "none",
      "affected_departments": []
    },
    "hiring_signals": {
      "hiring_velocity": "moderate",
      "hiring_freeze_score": 0.1
    },
    "role_risk_map": {
      "sales": 0.1,
      "designer": 0.1,
      "hr_recruiter": 0.1,
      "data_scientist": 0.1,
      "product_manager": 0.1,
      "software_engineer": 0.1
    },
    "ai_exposure_index": 0.5,
    "market_risk_score": 0.15,
    "company_risk_score": 0.1,
    "confidence_score": 0.95,
    "archetype": "mature_stable",
    "data_source": "expansion_batch_2026_real",
    "last_updated": "2026-04-28"
  },
  {
    "company_name": "AerCap Holdings N.V.",
    "industry": "Rental & Leasing Services",
    "company_size": "mid",
    "stage": "public",
    "workforce_count": 668,
    "open_jobs_count": 0,
    "financial_signals": {
      "burn_rate": "moderate",
      "funding_stage": "Public (NASDAQ/NYSE)",
      "revenue_trend": "stable",
      "months_since_last_funding": 120
    },
    "layoff_history": {
      "total_layoffs": 0,
      "last_layoff_date": "No History",
      "layoff_frequency": "none",
      "affected_departments": []
    },
    "hiring_signals": {
      "hiring_velocity": "moderate",
      "hiring_freeze_score": 0.1
    },
    "role_risk_map": {
      "sales": 0.1,
      "designer": 0.1,
      "hr_recruiter": 0.1,
      "data_scientist": 0.1,
      "product_manager": 0.1,
      "software_engineer": 0.1
    },
    "ai_exposure_index": 0.5,
    "market_risk_score": 0.15,
    "company_risk_score": 0.1,
    "confidence_score": 0.95,
    "archetype": "mature_stable",
    "data_source": "expansion_batch_2026_real",
    "last_updated": "2026-04-28"
  },
  {
    "company_name": "ALBEMARLE CORP",
    "industry": "Specialty Chemicals",
    "company_size": "enterprise",
    "stage": "public",
    "workforce_count": 7800,
    "open_jobs_count": 0,
    "financial_signals": {
      "burn_rate": "moderate",
      "funding_stage": "Public (NASDAQ/NYSE)",
      "revenue_trend": "stable",
      "months_since_last_funding": 120
    },
    "layoff_history": {
      "total_layoffs": 0,
      "last_layoff_date": "No History",
      "layoff_frequency": "none",
      "affected_departments": []
    },
    "hiring_signals": {
      "hiring_velocity": "moderate",
      "hiring_freeze_score": 0.1
    },
    "role_risk_map": {
      "sales": 0.1,
      "designer": 0.1,
      "hr_recruiter": 0.1,
      "data_scientist": 0.1,
      "product_manager": 0.1,
      "software_engineer": 0.1
    },
    "ai_exposure_index": 0.5,
    "market_risk_score": 0.15,
    "company_risk_score": 0.1,
    "confidence_score": 0.95,
    "archetype": "mature_stable",
    "data_source": "expansion_batch_2026_real",
    "last_updated": "2026-04-28"
  },
  {
    "company_name": "RALPH LAUREN CORP",
    "industry": "Apparel Manufacturing",
    "company_size": "global_giant",
    "stage": "public",
    "workforce_count": 15000,
    "open_jobs_count": 0,
    "financial_signals": {
      "burn_rate": "moderate",
      "funding_stage": "Public (NASDAQ/NYSE)",
      "revenue_trend": "stable",
      "months_since_last_funding": 120
    },
    "layoff_history": {
      "total_layoffs": 0,
      "last_layoff_date": "No History",
      "layoff_frequency": "none",
      "affected_departments": []
    },
    "hiring_signals": {
      "hiring_velocity": "moderate",
      "hiring_freeze_score": 0.1
    },
    "role_risk_map": {
      "sales": 0.1,
      "designer": 0.1,
      "hr_recruiter": 0.1,
      "data_scientist": 0.1,
      "product_manager": 0.1,
      "software_engineer": 0.1
    },
    "ai_exposure_index": 0.5,
    "market_risk_score": 0.15,
    "company_risk_score": 0.1,
    "confidence_score": 0.95,
    "archetype": "mature_stable",
    "data_source": "expansion_batch_2026_real",
    "last_updated": "2026-04-28"
  },
  {
    "company_name": "BCE INC",
    "industry": "Telecom Services",
    "company_size": "global_giant",
    "stage": "public",
    "workforce_count": 38683,
    "open_jobs_count": 0,
    "financial_signals": {
      "burn_rate": "moderate",
      "funding_stage": "Public (NASDAQ/NYSE)",
      "revenue_trend": "stable",
      "months_since_last_funding": 120
    },
    "layoff_history": {
      "total_layoffs": 0,
      "last_layoff_date": "No History",
      "layoff_frequency": "none",
      "affected_departments": []
    },
    "hiring_signals": {
      "hiring_velocity": "moderate",
      "hiring_freeze_score": 0.1
    },
    "role_risk_map": {
      "sales": 0.1,
      "designer": 0.1,
      "hr_recruiter": 0.1,
      "data_scientist": 0.1,
      "product_manager": 0.1,
      "software_engineer": 0.1
    },
    "ai_exposure_index": 0.5,
    "market_risk_score": 0.15,
    "company_risk_score": 0.1,
    "confidence_score": 0.95,
    "archetype": "mature_stable",
    "data_source": "expansion_batch_2026_real",
    "last_updated": "2026-04-28"
  },
  {
    "company_name": "CHURCH & DWIGHT CO INC /DE/",
    "industry": "Household & Personal Products",
    "company_size": "enterprise",
    "stage": "public",
    "workforce_count": 5550,
    "open_jobs_count": 0,
    "financial_signals": {
      "burn_rate": "moderate",
      "funding_stage": "Public (NASDAQ/NYSE)",
      "revenue_trend": "stable",
      "months_since_last_funding": 120
    },
    "layoff_history": {
      "total_layoffs": 0,
      "last_layoff_date": "No History",
      "layoff_frequency": "none",
      "affected_departments": []
    },
    "hiring_signals": {
      "hiring_velocity": "moderate",
      "hiring_freeze_score": 0.1
    },
    "role_risk_map": {
      "sales": 0.1,
      "designer": 0.1,
      "hr_recruiter": 0.1,
      "data_scientist": 0.1,
      "product_manager": 0.1,
      "software_engineer": 0.1
    },
    "ai_exposure_index": 0.5,
    "market_risk_score": 0.15,
    "company_risk_score": 0.1,
    "confidence_score": 0.95,
    "archetype": "mature_stable",
    "data_source": "expansion_batch_2026_real",
    "last_updated": "2026-04-28"
  },
  {
    "company_name": "WEST PHARMACEUTICAL SERVICES INC",
    "industry": "Medical Instruments & Supplies",
    "company_size": "global_giant",
    "stage": "public",
    "workforce_count": 10800,
    "open_jobs_count": 0,
    "financial_signals": {
      "burn_rate": "moderate",
      "funding_stage": "Public (NASDAQ/NYSE)",
      "revenue_trend": "stable",
      "months_since_last_funding": 120
    },
    "layoff_history": {
      "total_layoffs": 0,
      "last_layoff_date": "No History",
      "layoff_frequency": "none",
      "affected_departments": []
    },
    "hiring_signals": {
      "hiring_velocity": "moderate",
      "hiring_freeze_score": 0.1
    },
    "role_risk_map": {
      "sales": 0.1,
      "designer": 0.1,
      "hr_recruiter": 0.1,
      "data_scientist": 0.1,
      "product_manager": 0.1,
      "software_engineer": 0.1
    },
    "ai_exposure_index": 0.5,
    "market_risk_score": 0.15,
    "company_risk_score": 0.1,
    "confidence_score": 0.95,
    "archetype": "mature_stable",
    "data_source": "expansion_batch_2026_real",
    "last_updated": "2026-04-28"
  },
  {
    "company_name": "QUEST DIAGNOSTICS INC",
    "industry": "Diagnostics & Research",
    "company_size": "global_giant",
    "stage": "public",
    "workforce_count": 57000,
    "open_jobs_count": 0,
    "financial_signals": {
      "burn_rate": "moderate",
      "funding_stage": "Public (NASDAQ/NYSE)",
      "revenue_trend": "stable",
      "months_since_last_funding": 120
    },
    "layoff_history": {
      "total_layoffs": 0,
      "last_layoff_date": "No History",
      "layoff_frequency": "none",
      "affected_departments": []
    },
    "hiring_signals": {
      "hiring_velocity": "moderate",
      "hiring_freeze_score": 0.1
    },
    "role_risk_map": {
      "sales": 0.1,
      "designer": 0.1,
      "hr_recruiter": 0.1,
      "data_scientist": 0.1,
      "product_manager": 0.1,
      "software_engineer": 0.1
    },
    "ai_exposure_index": 0.5,
    "market_risk_score": 0.15,
    "company_risk_score": 0.1,
    "confidence_score": 0.95,
    "archetype": "mature_stable",
    "data_source": "expansion_batch_2026_real",
    "last_updated": "2026-04-28"
  },
  {
    "company_name": "STERIS plc",
    "industry": "Medical Devices",
    "company_size": "global_giant",
    "stage": "public",
    "workforce_count": 17787,
    "open_jobs_count": 0,
    "financial_signals": {
      "burn_rate": "moderate",
      "funding_stage": "Public (NASDAQ/NYSE)",
      "revenue_trend": "stable",
      "months_since_last_funding": 120
    },
    "layoff_history": {
      "total_layoffs": 0,
      "last_layoff_date": "No History",
      "layoff_frequency": "none",
      "affected_departments": []
    },
    "hiring_signals": {
      "hiring_velocity": "moderate",
      "hiring_freeze_score": 0.1
    },
    "role_risk_map": {
      "sales": 0.1,
      "designer": 0.1,
      "hr_recruiter": 0.1,
      "data_scientist": 0.1,
      "product_manager": 0.1,
      "software_engineer": 0.1
    },
    "ai_exposure_index": 0.5,
    "market_risk_score": 0.15,
    "company_risk_score": 0.1,
    "confidence_score": 0.95,
    "archetype": "mature_stable",
    "data_source": "expansion_batch_2026_real",
    "last_updated": "2026-04-28"
  },
  {
    "company_name": "Woodward, Inc.",
    "industry": "Aerospace & Defense",
    "company_size": "global_giant",
    "stage": "public",
    "workforce_count": 10200,
    "open_jobs_count": 0,
    "financial_signals": {
      "burn_rate": "moderate",
      "funding_stage": "Public (NASDAQ/NYSE)",
      "revenue_trend": "stable",
      "months_since_last_funding": 120
    },
    "layoff_history": {
      "total_layoffs": 0,
      "last_layoff_date": "No History",
      "layoff_frequency": "none",
      "affected_departments": []
    },
    "hiring_signals": {
      "hiring_velocity": "moderate",
      "hiring_freeze_score": 0.1
    },
    "role_risk_map": {
      "sales": 0.1,
      "designer": 0.1,
      "hr_recruiter": 0.1,
      "data_scientist": 0.1,
      "product_manager": 0.1,
      "software_engineer": 0.1
    },
    "ai_exposure_index": 0.5,
    "market_risk_score": 0.15,
    "company_risk_score": 0.1,
    "confidence_score": 0.95,
    "archetype": "mature_stable",
    "data_source": "expansion_batch_2026_real",
    "last_updated": "2026-04-28"
  },
  {
    "company_name": "LABCORP HOLDINGS INC.",
    "industry": "Diagnostics & Research",
    "company_size": "global_giant",
    "stage": "public",
    "workforce_count": 61770,
    "open_jobs_count": 0,
    "financial_signals": {
      "burn_rate": "moderate",
      "funding_stage": "Public (NASDAQ/NYSE)",
      "revenue_trend": "stable",
      "months_since_last_funding": 120
    },
    "layoff_history": {
      "total_layoffs": 0,
      "last_layoff_date": "No History",
      "layoff_frequency": "none",
      "affected_departments": []
    },
    "hiring_signals": {
      "hiring_velocity": "moderate",
      "hiring_freeze_score": 0.1
    },
    "role_risk_map": {
      "sales": 0.1,
      "designer": 0.1,
      "hr_recruiter": 0.1,
      "data_scientist": 0.1,
      "product_manager": 0.1,
      "software_engineer": 0.1
    },
    "ai_exposure_index": 0.5,
    "market_risk_score": 0.15,
    "company_risk_score": 0.1,
    "confidence_score": 0.95,
    "archetype": "mature_stable",
    "data_source": "expansion_batch_2026_real",
    "last_updated": "2026-04-28"
  },
  {
    "company_name": "Veralto Corp",
    "industry": "Pollution & Treatment Controls",
    "company_size": "global_giant",
    "stage": "public",
    "workforce_count": 16500,
    "open_jobs_count": 0,
    "financial_signals": {
      "burn_rate": "moderate",
      "funding_stage": "Public (NASDAQ/NYSE)",
      "revenue_trend": "stable",
      "months_since_last_funding": 120
    },
    "layoff_history": {
      "total_layoffs": 0,
      "last_layoff_date": "No History",
      "layoff_frequency": "none",
      "affected_departments": []
    },
    "hiring_signals": {
      "hiring_velocity": "moderate",
      "hiring_freeze_score": 0.1
    },
    "role_risk_map": {
      "sales": 0.1,
      "designer": 0.1,
      "hr_recruiter": 0.1,
      "data_scientist": 0.1,
      "product_manager": 0.1,
      "software_engineer": 0.1
    },
    "ai_exposure_index": 0.5,
    "market_risk_score": 0.15,
    "company_risk_score": 0.1,
    "confidence_score": 0.95,
    "archetype": "mature_stable",
    "data_source": "expansion_batch_2026_real",
    "last_updated": "2026-04-28"
  },
  {
    "company_name": "C. H. ROBINSON WORLDWIDE, INC.",
    "industry": "Integrated Freight & Logistics",
    "company_size": "global_giant",
    "stage": "public",
    "workforce_count": 11736,
    "open_jobs_count": 0,
    "financial_signals": {
      "burn_rate": "moderate",
      "funding_stage": "Public (NASDAQ/NYSE)",
      "revenue_trend": "stable",
      "months_since_last_funding": 120
    },
    "layoff_history": {
      "total_layoffs": 0,
      "last_layoff_date": "No History",
      "layoff_frequency": "none",
      "affected_departments": []
    },
    "hiring_signals": {
      "hiring_velocity": "moderate",
      "hiring_freeze_score": 0.1
    },
    "role_risk_map": {
      "sales": 0.1,
      "designer": 0.1,
      "hr_recruiter": 0.1,
      "data_scientist": 0.1,
      "product_manager": 0.1,
      "software_engineer": 0.1
    },
    "ai_exposure_index": 0.5,
    "market_risk_score": 0.15,
    "company_risk_score": 0.1,
    "confidence_score": 0.95,
    "archetype": "mature_stable",
    "data_source": "expansion_batch_2026_real",
    "last_updated": "2026-04-28"
  },
  {
    "company_name": "PRICE T ROWE GROUP INC",
    "industry": "Asset Management",
    "company_size": "enterprise",
    "stage": "public",
    "workforce_count": 7773,
    "open_jobs_count": 0,
    "financial_signals": {
      "burn_rate": "moderate",
      "funding_stage": "Public (NASDAQ/NYSE)",
      "revenue_trend": "stable",
      "months_since_last_funding": 120
    },
    "layoff_history": {
      "total_layoffs": 0,
      "last_layoff_date": "No History",
      "layoff_frequency": "none",
      "affected_departments": []
    },
    "hiring_signals": {
      "hiring_velocity": "moderate",
      "hiring_freeze_score": 0.1
    },
    "role_risk_map": {
      "sales": 0.1,
      "designer": 0.1,
      "hr_recruiter": 0.1,
      "data_scientist": 0.1,
      "product_manager": 0.1,
      "software_engineer": 0.1
    },
    "ai_exposure_index": 0.5,
    "market_risk_score": 0.15,
    "company_risk_score": 0.1,
    "confidence_score": 0.95,
    "archetype": "mature_stable",
    "data_source": "expansion_batch_2026_real",
    "last_updated": "2026-04-28"
  },
  {
    "company_name": "EDP ENERGIAS DE PORTUGAL SA",
    "industry": "Utilities - Diversified",
    "company_size": "global_giant",
    "stage": "public",
    "workforce_count": 11858,
    "open_jobs_count": 0,
    "financial_signals": {
      "burn_rate": "moderate",
      "funding_stage": "Public (NASDAQ/NYSE)",
      "revenue_trend": "stable",
      "months_since_last_funding": 120
    },
    "layoff_history": {
      "total_layoffs": 0,
      "last_layoff_date": "No History",
      "layoff_frequency": "none",
      "affected_departments": []
    },
    "hiring_signals": {
      "hiring_velocity": "moderate",
      "hiring_freeze_score": 0.1
    },
    "role_risk_map": {
      "sales": 0.1,
      "designer": 0.1,
      "hr_recruiter": 0.1,
      "data_scientist": 0.1,
      "product_manager": 0.1,
      "software_engineer": 0.1
    },
    "ai_exposure_index": 0.5,
    "market_risk_score": 0.15,
    "company_risk_score": 0.1,
    "confidence_score": 0.95,
    "archetype": "mature_stable",
    "data_source": "expansion_batch_2026_real",
    "last_updated": "2026-04-28"
  },
  {
    "company_name": "Futu Holdings Ltd",
    "industry": "Capital Markets",
    "company_size": "large",
    "stage": "public",
    "workforce_count": 3540,
    "open_jobs_count": 0,
    "financial_signals": {
      "burn_rate": "moderate",
      "funding_stage": "Public (NASDAQ/NYSE)",
      "revenue_trend": "stable",
      "months_since_last_funding": 120
    },
    "layoff_history": {
      "total_layoffs": 0,
      "last_layoff_date": "No History",
      "layoff_frequency": "none",
      "affected_departments": []
    },
    "hiring_signals": {
      "hiring_velocity": "moderate",
      "hiring_freeze_score": 0.1
    },
    "role_risk_map": {
      "sales": 0.1,
      "designer": 0.1,
      "hr_recruiter": 0.1,
      "data_scientist": 0.1,
      "product_manager": 0.1,
      "software_engineer": 0.1
    },
    "ai_exposure_index": 0.5,
    "market_risk_score": 0.15,
    "company_risk_score": 0.1,
    "confidence_score": 0.95,
    "archetype": "mature_stable",
    "data_source": "expansion_batch_2026_real",
    "last_updated": "2026-04-28"
  },
  {
    "company_name": "NetApp, Inc.",
    "industry": "Software - Infrastructure",
    "company_size": "global_giant",
    "stage": "public",
    "workforce_count": 11700,
    "open_jobs_count": 0,
    "financial_signals": {
      "burn_rate": "moderate",
      "funding_stage": "Public (NASDAQ/NYSE)",
      "revenue_trend": "stable",
      "months_since_last_funding": 120
    },
    "layoff_history": {
      "total_layoffs": 0,
      "last_layoff_date": "No History",
      "layoff_frequency": "none",
      "affected_departments": []
    },
    "hiring_signals": {
      "hiring_velocity": "moderate",
      "hiring_freeze_score": 0.1
    },
    "role_risk_map": {
      "sales": 0.1,
      "designer": 0.1,
      "hr_recruiter": 0.1,
      "data_scientist": 0.1,
      "product_manager": 0.1,
      "software_engineer": 0.1
    },
    "ai_exposure_index": 0.5,
    "market_risk_score": 0.15,
    "company_risk_score": 0.1,
    "confidence_score": 0.95,
    "archetype": "mature_stable",
    "data_source": "expansion_batch_2026_real",
    "last_updated": "2026-04-28"
  },
  {
    "company_name": "TWILIO INC",
    "industry": "Software - Infrastructure",
    "company_size": "enterprise",
    "stage": "public",
    "workforce_count": 5587,
    "open_jobs_count": 0,
    "financial_signals": {
      "burn_rate": "moderate",
      "funding_stage": "Public (NASDAQ/NYSE)",
      "revenue_trend": "stable",
      "months_since_last_funding": 120
    },
    "layoff_history": {
      "total_layoffs": 0,
      "last_layoff_date": "No History",
      "layoff_frequency": "none",
      "affected_departments": []
    },
    "hiring_signals": {
      "hiring_velocity": "moderate",
      "hiring_freeze_score": 0.1
    },
    "role_risk_map": {
      "sales": 0.1,
      "designer": 0.1,
      "hr_recruiter": 0.1,
      "data_scientist": 0.1,
      "product_manager": 0.1,
      "software_engineer": 0.1
    },
    "ai_exposure_index": 0.5,
    "market_risk_score": 0.15,
    "company_risk_score": 0.1,
    "confidence_score": 0.95,
    "archetype": "mature_stable",
    "data_source": "expansion_batch_2026_real",
    "last_updated": "2026-04-28"
  },
  {
    "company_name": "INTERCONTINENTAL HOTELS GROUP PLC /NEW/",
    "industry": "Lodging",
    "company_size": "global_giant",
    "stage": "public",
    "workforce_count": 13049,
    "open_jobs_count": 0,
    "financial_signals": {
      "burn_rate": "moderate",
      "funding_stage": "Public (NASDAQ/NYSE)",
      "revenue_trend": "stable",
      "months_since_last_funding": 120
    },
    "layoff_history": {
      "total_layoffs": 0,
      "last_layoff_date": "No History",
      "layoff_frequency": "none",
      "affected_departments": []
    },
    "hiring_signals": {
      "hiring_velocity": "moderate",
      "hiring_freeze_score": 0.1
    },
    "role_risk_map": {
      "sales": 0.1,
      "designer": 0.1,
      "hr_recruiter": 0.1,
      "data_scientist": 0.1,
      "product_manager": 0.1,
      "software_engineer": 0.1
    },
    "ai_exposure_index": 0.5,
    "market_risk_score": 0.15,
    "company_risk_score": 0.1,
    "confidence_score": 0.95,
    "archetype": "mature_stable",
    "data_source": "expansion_batch_2026_real",
    "last_updated": "2026-04-28"
  },
  {
    "company_name": "COCA COLA FEMSA SAB DE CV",
    "industry": "Beverages - Non-Alcoholic",
    "company_size": "global_giant",
    "stage": "public",
    "workforce_count": 93000,
    "open_jobs_count": 0,
    "financial_signals": {
      "burn_rate": "moderate",
      "funding_stage": "Public (NASDAQ/NYSE)",
      "revenue_trend": "stable",
      "months_since_last_funding": 120
    },
    "layoff_history": {
      "total_layoffs": 0,
      "last_layoff_date": "No History",
      "layoff_frequency": "none",
      "affected_departments": []
    },
    "hiring_signals": {
      "hiring_velocity": "moderate",
      "hiring_freeze_score": 0.1
    },
    "role_risk_map": {
      "sales": 0.1,
      "designer": 0.1,
      "hr_recruiter": 0.1,
      "data_scientist": 0.1,
      "product_manager": 0.1,
      "software_engineer": 0.1
    },
    "ai_exposure_index": 0.5,
    "market_risk_score": 0.15,
    "company_risk_score": 0.1,
    "confidence_score": 0.95,
    "archetype": "mature_stable",
    "data_source": "expansion_batch_2026_real",
    "last_updated": "2026-04-28"
  },
  {
    "company_name": "Zscaler, Inc.",
    "industry": "Software - Infrastructure",
    "company_size": "enterprise",
    "stage": "public",
    "workforce_count": 7923,
    "open_jobs_count": 0,
    "financial_signals": {
      "burn_rate": "moderate",
      "funding_stage": "Public (NASDAQ/NYSE)",
      "revenue_trend": "stable",
      "months_since_last_funding": 120
    },
    "layoff_history": {
      "total_layoffs": 0,
      "last_layoff_date": "No History",
      "layoff_frequency": "none",
      "affected_departments": []
    },
    "hiring_signals": {
      "hiring_velocity": "moderate",
      "hiring_freeze_score": 0.1
    },
    "role_risk_map": {
      "sales": 0.1,
      "designer": 0.1,
      "hr_recruiter": 0.1,
      "data_scientist": 0.1,
      "product_manager": 0.1,
      "software_engineer": 0.1
    },
    "ai_exposure_index": 0.5,
    "market_risk_score": 0.15,
    "company_risk_score": 0.1,
    "confidence_score": 0.95,
    "archetype": "mature_stable",
    "data_source": "expansion_batch_2026_real",
    "last_updated": "2026-04-28"
  },
  {
    "company_name": "MACOM Technology Solutions Holdings, Inc.",
    "industry": "Semiconductors",
    "company_size": "large",
    "stage": "public",
    "workforce_count": 2000,
    "open_jobs_count": 0,
    "financial_signals": {
      "burn_rate": "moderate",
      "funding_stage": "Public (NASDAQ/NYSE)",
      "revenue_trend": "stable",
      "months_since_last_funding": 120
    },
    "layoff_history": {
      "total_layoffs": 0,
      "last_layoff_date": "No History",
      "layoff_frequency": "none",
      "affected_departments": []
    },
    "hiring_signals": {
      "hiring_velocity": "moderate",
      "hiring_freeze_score": 0.1
    },
    "role_risk_map": {
      "sales": 0.1,
      "designer": 0.1,
      "hr_recruiter": 0.1,
      "data_scientist": 0.1,
      "product_manager": 0.1,
      "software_engineer": 0.1
    },
    "ai_exposure_index": 0.5,
    "market_risk_score": 0.15,
    "company_risk_score": 0.1,
    "confidence_score": 0.95,
    "archetype": "mature_stable",
    "data_source": "expansion_batch_2026_real",
    "last_updated": "2026-04-28"
  },
  {
    "company_name": "ROYAL GOLD INC",
    "industry": "Gold",
    "company_size": "mid",
    "stage": "public",
    "workforce_count": 39,
    "open_jobs_count": 0,
    "financial_signals": {
      "burn_rate": "moderate",
      "funding_stage": "Public (NASDAQ/NYSE)",
      "revenue_trend": "stable",
      "months_since_last_funding": 120
    },
    "layoff_history": {
      "total_layoffs": 0,
      "last_layoff_date": "No History",
      "layoff_frequency": "none",
      "affected_departments": []
    },
    "hiring_signals": {
      "hiring_velocity": "moderate",
      "hiring_freeze_score": 0.1
    },
    "role_risk_map": {
      "sales": 0.1,
      "designer": 0.1,
      "hr_recruiter": 0.1,
      "data_scientist": 0.1,
      "product_manager": 0.1,
      "software_engineer": 0.1
    },
    "ai_exposure_index": 0.5,
    "market_risk_score": 0.15,
    "company_risk_score": 0.1,
    "confidence_score": 0.95,
    "archetype": "mature_stable",
    "data_source": "expansion_batch_2026_real",
    "last_updated": "2026-04-28"
  },
  {
    "company_name": "Smurfit Westrock plc",
    "industry": "Packaging & Containers",
    "company_size": "global_giant",
    "stage": "public",
    "workforce_count": 97000,
    "open_jobs_count": 0,
    "financial_signals": {
      "burn_rate": "moderate",
      "funding_stage": "Public (NASDAQ/NYSE)",
      "revenue_trend": "stable",
      "months_since_last_funding": 120
    },
    "layoff_history": {
      "total_layoffs": 0,
      "last_layoff_date": "No History",
      "layoff_frequency": "none",
      "affected_departments": []
    },
    "hiring_signals": {
      "hiring_velocity": "moderate",
      "hiring_freeze_score": 0.1
    },
    "role_risk_map": {
      "sales": 0.1,
      "designer": 0.1,
      "hr_recruiter": 0.1,
      "data_scientist": 0.1,
      "product_manager": 0.1,
      "software_engineer": 0.1
    },
    "ai_exposure_index": 0.5,
    "market_risk_score": 0.15,
    "company_risk_score": 0.1,
    "confidence_score": 0.95,
    "archetype": "mature_stable",
    "data_source": "expansion_batch_2026_real",
    "last_updated": "2026-04-28"
  },
  {
    "company_name": "CARPENTER TECHNOLOGY CORP",
    "industry": "Metal Fabrication",
    "company_size": "large",
    "stage": "public",
    "workforce_count": 4500,
    "open_jobs_count": 0,
    "financial_signals": {
      "burn_rate": "moderate",
      "funding_stage": "Public (NASDAQ/NYSE)",
      "revenue_trend": "stable",
      "months_since_last_funding": 120
    },
    "layoff_history": {
      "total_layoffs": 0,
      "last_layoff_date": "No History",
      "layoff_frequency": "none",
      "affected_departments": []
    },
    "hiring_signals": {
      "hiring_velocity": "moderate",
      "hiring_freeze_score": 0.1
    },
    "role_risk_map": {
      "sales": 0.1,
      "designer": 0.1,
      "hr_recruiter": 0.1,
      "data_scientist": 0.1,
      "product_manager": 0.1,
      "software_engineer": 0.1
    },
    "ai_exposure_index": 0.5,
    "market_risk_score": 0.15,
    "company_risk_score": 0.1,
    "confidence_score": 0.95,
    "archetype": "mature_stable",
    "data_source": "expansion_batch_2026_real",
    "last_updated": "2026-04-28"
  },
  {
    "company_name": "EQUIFAX INC",
    "industry": "Consulting Services",
    "company_size": "global_giant",
    "stage": "public",
    "workforce_count": 15000,
    "open_jobs_count": 0,
    "financial_signals": {
      "burn_rate": "moderate",
      "funding_stage": "Public (NASDAQ/NYSE)",
      "revenue_trend": "stable",
      "months_since_last_funding": 120
    },
    "layoff_history": {
      "total_layoffs": 0,
      "last_layoff_date": "No History",
      "layoff_frequency": "none",
      "affected_departments": []
    },
    "hiring_signals": {
      "hiring_velocity": "moderate",
      "hiring_freeze_score": 0.1
    },
    "role_risk_map": {
      "sales": 0.1,
      "designer": 0.1,
      "hr_recruiter": 0.1,
      "data_scientist": 0.1,
      "product_manager": 0.1,
      "software_engineer": 0.1
    },
    "ai_exposure_index": 0.5,
    "market_risk_score": 0.15,
    "company_risk_score": 0.1,
    "confidence_score": 0.95,
    "archetype": "mature_stable",
    "data_source": "expansion_batch_2026_real",
    "last_updated": "2026-04-28"
  },
  {
    "company_name": "FIRST SOLAR, INC.",
    "industry": "Solar",
    "company_size": "enterprise",
    "stage": "public",
    "workforce_count": 7900,
    "open_jobs_count": 0,
    "financial_signals": {
      "burn_rate": "moderate",
      "funding_stage": "Public (NASDAQ/NYSE)",
      "revenue_trend": "stable",
      "months_since_last_funding": 120
    },
    "layoff_history": {
      "total_layoffs": 0,
      "last_layoff_date": "No History",
      "layoff_frequency": "none",
      "affected_departments": []
    },
    "hiring_signals": {
      "hiring_velocity": "moderate",
      "hiring_freeze_score": 0.1
    },
    "role_risk_map": {
      "sales": 0.1,
      "designer": 0.1,
      "hr_recruiter": 0.1,
      "data_scientist": 0.1,
      "product_manager": 0.1,
      "software_engineer": 0.1
    },
    "ai_exposure_index": 0.5,
    "market_risk_score": 0.15,
    "company_risk_score": 0.1,
    "confidence_score": 0.95,
    "archetype": "mature_stable",
    "data_source": "expansion_batch_2026_real",
    "last_updated": "2026-04-28"
  },
  {
    "company_name": "APi Group Corp",
    "industry": "Engineering & Construction",
    "company_size": "global_giant",
    "stage": "public",
    "workforce_count": 29000,
    "open_jobs_count": 0,
    "financial_signals": {
      "burn_rate": "moderate",
      "funding_stage": "Public (NASDAQ/NYSE)",
      "revenue_trend": "stable",
      "months_since_last_funding": 120
    },
    "layoff_history": {
      "total_layoffs": 0,
      "last_layoff_date": "No History",
      "layoff_frequency": "none",
      "affected_departments": []
    },
    "hiring_signals": {
      "hiring_velocity": "moderate",
      "hiring_freeze_score": 0.1
    },
    "role_risk_map": {
      "sales": 0.1,
      "designer": 0.1,
      "hr_recruiter": 0.1,
      "data_scientist": 0.1,
      "product_manager": 0.1,
      "software_engineer": 0.1
    },
    "ai_exposure_index": 0.5,
    "market_risk_score": 0.15,
    "company_risk_score": 0.1,
    "confidence_score": 0.95,
    "archetype": "mature_stable",
    "data_source": "expansion_batch_2026_real",
    "last_updated": "2026-04-28"
  },
  {
    "company_name": "Rivian Automotive, Inc. / DE",
    "industry": "Auto Manufacturers",
    "company_size": "global_giant",
    "stage": "public",
    "workforce_count": 15232,
    "open_jobs_count": 0,
    "financial_signals": {
      "burn_rate": "moderate",
      "funding_stage": "Public (NASDAQ/NYSE)",
      "revenue_trend": "stable",
      "months_since_last_funding": 120
    },
    "layoff_history": {
      "total_layoffs": 0,
      "last_layoff_date": "No History",
      "layoff_frequency": "none",
      "affected_departments": []
    },
    "hiring_signals": {
      "hiring_velocity": "moderate",
      "hiring_freeze_score": 0.1
    },
    "role_risk_map": {
      "sales": 0.1,
      "designer": 0.1,
      "hr_recruiter": 0.1,
      "data_scientist": 0.1,
      "product_manager": 0.1,
      "software_engineer": 0.1
    },
    "ai_exposure_index": 0.5,
    "market_risk_score": 0.15,
    "company_risk_score": 0.1,
    "confidence_score": 0.95,
    "archetype": "mature_stable",
    "data_source": "expansion_batch_2026_real",
    "last_updated": "2026-04-28"
  },
  {
    "company_name": "PRINCIPAL FINANCIAL GROUP INC",
    "industry": "Asset Management",
    "company_size": "global_giant",
    "stage": "public",
    "workforce_count": 19700,
    "open_jobs_count": 0,
    "financial_signals": {
      "burn_rate": "moderate",
      "funding_stage": "Public (NASDAQ/NYSE)",
      "revenue_trend": "stable",
      "months_since_last_funding": 120
    },
    "layoff_history": {
      "total_layoffs": 0,
      "last_layoff_date": "No History",
      "layoff_frequency": "none",
      "affected_departments": []
    },
    "hiring_signals": {
      "hiring_velocity": "moderate",
      "hiring_freeze_score": 0.1
    },
    "role_risk_map": {
      "sales": 0.1,
      "designer": 0.1,
      "hr_recruiter": 0.1,
      "data_scientist": 0.1,
      "product_manager": 0.1,
      "software_engineer": 0.1
    },
    "ai_exposure_index": 0.5,
    "market_risk_score": 0.15,
    "company_risk_score": 0.1,
    "confidence_score": 0.95,
    "archetype": "mature_stable",
    "data_source": "expansion_batch_2026_real",
    "last_updated": "2026-04-28"
  },
  {
    "company_name": "ATI INC",
    "industry": "Metal Fabrication",
    "company_size": "enterprise",
    "stage": "public",
    "workforce_count": 7600,
    "open_jobs_count": 0,
    "financial_signals": {
      "burn_rate": "moderate",
      "funding_stage": "Public (NASDAQ/NYSE)",
      "revenue_trend": "stable",
      "months_since_last_funding": 120
    },
    "layoff_history": {
      "total_layoffs": 0,
      "last_layoff_date": "No History",
      "layoff_frequency": "none",
      "affected_departments": []
    },
    "hiring_signals": {
      "hiring_velocity": "moderate",
      "hiring_freeze_score": 0.1
    },
    "role_risk_map": {
      "sales": 0.1,
      "designer": 0.1,
      "hr_recruiter": 0.1,
      "data_scientist": 0.1,
      "product_manager": 0.1,
      "software_engineer": 0.1
    },
    "ai_exposure_index": 0.5,
    "market_risk_score": 0.15,
    "company_risk_score": 0.1,
    "confidence_score": 0.95,
    "archetype": "mature_stable",
    "data_source": "expansion_batch_2026_real",
    "last_updated": "2026-04-28"
  },
  {
    "company_name": "Amer Sports, Inc.",
    "industry": "Leisure",
    "company_size": "global_giant",
    "stage": "public",
    "workforce_count": 15400,
    "open_jobs_count": 0,
    "financial_signals": {
      "burn_rate": "moderate",
      "funding_stage": "Public (NASDAQ/NYSE)",
      "revenue_trend": "stable",
      "months_since_last_funding": 120
    },
    "layoff_history": {
      "total_layoffs": 0,
      "last_layoff_date": "No History",
      "layoff_frequency": "none",
      "affected_departments": []
    },
    "hiring_signals": {
      "hiring_velocity": "moderate",
      "hiring_freeze_score": 0.1
    },
    "role_risk_map": {
      "sales": 0.1,
      "designer": 0.1,
      "hr_recruiter": 0.1,
      "data_scientist": 0.1,
      "product_manager": 0.1,
      "software_engineer": 0.1
    },
    "ai_exposure_index": 0.5,
    "market_risk_score": 0.15,
    "company_risk_score": 0.1,
    "confidence_score": 0.95,
    "archetype": "mature_stable",
    "data_source": "expansion_batch_2026_real",
    "last_updated": "2026-04-28"
  },
  {
    "company_name": "Affirm Holdings, Inc.",
    "industry": "Credit Services",
    "company_size": "large",
    "stage": "public",
    "workforce_count": 2206,
    "open_jobs_count": 0,
    "financial_signals": {
      "burn_rate": "moderate",
      "funding_stage": "Public (NASDAQ/NYSE)",
      "revenue_trend": "stable",
      "months_since_last_funding": 120
    },
    "layoff_history": {
      "total_layoffs": 0,
      "last_layoff_date": "No History",
      "layoff_frequency": "none",
      "affected_departments": []
    },
    "hiring_signals": {
      "hiring_velocity": "moderate",
      "hiring_freeze_score": 0.1
    },
    "role_risk_map": {
      "sales": 0.1,
      "designer": 0.1,
      "hr_recruiter": 0.1,
      "data_scientist": 0.1,
      "product_manager": 0.1,
      "software_engineer": 0.1
    },
    "ai_exposure_index": 0.5,
    "market_risk_score": 0.15,
    "company_risk_score": 0.1,
    "confidence_score": 0.95,
    "archetype": "mature_stable",
    "data_source": "expansion_batch_2026_real",
    "last_updated": "2026-04-28"
  },
  {
    "company_name": "MongoDB, Inc.",
    "industry": "Software - Infrastructure",
    "company_size": "enterprise",
    "stage": "public",
    "workforce_count": 5636,
    "open_jobs_count": 0,
    "financial_signals": {
      "burn_rate": "moderate",
      "funding_stage": "Public (NASDAQ/NYSE)",
      "revenue_trend": "stable",
      "months_since_last_funding": 120
    },
    "layoff_history": {
      "total_layoffs": 0,
      "last_layoff_date": "No History",
      "layoff_frequency": "none",
      "affected_departments": []
    },
    "hiring_signals": {
      "hiring_velocity": "moderate",
      "hiring_freeze_score": 0.1
    },
    "role_risk_map": {
      "sales": 0.1,
      "designer": 0.1,
      "hr_recruiter": 0.1,
      "data_scientist": 0.1,
      "product_manager": 0.1,
      "software_engineer": 0.1
    },
    "ai_exposure_index": 0.5,
    "market_risk_score": 0.15,
    "company_risk_score": 0.1,
    "confidence_score": 0.95,
    "archetype": "mature_stable",
    "data_source": "expansion_batch_2026_real",
    "last_updated": "2026-04-28"
  },
  {
    "company_name": "CORPAY, INC.",
    "industry": "Software - Infrastructure",
    "company_size": "global_giant",
    "stage": "public",
    "workforce_count": 11800,
    "open_jobs_count": 0,
    "financial_signals": {
      "burn_rate": "moderate",
      "funding_stage": "Public (NASDAQ/NYSE)",
      "revenue_trend": "stable",
      "months_since_last_funding": 120
    },
    "layoff_history": {
      "total_layoffs": 0,
      "last_layoff_date": "No History",
      "layoff_frequency": "none",
      "affected_departments": []
    },
    "hiring_signals": {
      "hiring_velocity": "moderate",
      "hiring_freeze_score": 0.1
    },
    "role_risk_map": {
      "sales": 0.1,
      "designer": 0.1,
      "hr_recruiter": 0.1,
      "data_scientist": 0.1,
      "product_manager": 0.1,
      "software_engineer": 0.1
    },
    "ai_exposure_index": 0.5,
    "market_risk_score": 0.15,
    "company_risk_score": 0.1,
    "confidence_score": 0.95,
    "archetype": "mature_stable",
    "data_source": "expansion_batch_2026_real",
    "last_updated": "2026-04-28"
  },
  {
    "company_name": "Burlington Stores, Inc.",
    "industry": "Apparel Retail",
    "company_size": "global_giant",
    "stage": "public",
    "workforce_count": 17495,
    "open_jobs_count": 0,
    "financial_signals": {
      "burn_rate": "moderate",
      "funding_stage": "Public (NASDAQ/NYSE)",
      "revenue_trend": "stable",
      "months_since_last_funding": 120
    },
    "layoff_history": {
      "total_layoffs": 0,
      "last_layoff_date": "No History",
      "layoff_frequency": "none",
      "affected_departments": []
    },
    "hiring_signals": {
      "hiring_velocity": "moderate",
      "hiring_freeze_score": 0.1
    },
    "role_risk_map": {
      "sales": 0.1,
      "designer": 0.1,
      "hr_recruiter": 0.1,
      "data_scientist": 0.1,
      "product_manager": 0.1,
      "software_engineer": 0.1
    },
    "ai_exposure_index": 0.5,
    "market_risk_score": 0.15,
    "company_risk_score": 0.1,
    "confidence_score": 0.95,
    "archetype": "mature_stable",
    "data_source": "expansion_batch_2026_real",
    "last_updated": "2026-04-28"
  },
  {
    "company_name": "BWX Technologies, Inc.",
    "industry": "Aerospace & Defense",
    "company_size": "global_giant",
    "stage": "public",
    "workforce_count": 10400,
    "open_jobs_count": 0,
    "financial_signals": {
      "burn_rate": "moderate",
      "funding_stage": "Public (NASDAQ/NYSE)",
      "revenue_trend": "stable",
      "months_since_last_funding": 120
    },
    "layoff_history": {
      "total_layoffs": 0,
      "last_layoff_date": "No History",
      "layoff_frequency": "none",
      "affected_departments": []
    },
    "hiring_signals": {
      "hiring_velocity": "moderate",
      "hiring_freeze_score": 0.1
    },
    "role_risk_map": {
      "sales": 0.1,
      "designer": 0.1,
      "hr_recruiter": 0.1,
      "data_scientist": 0.1,
      "product_manager": 0.1,
      "software_engineer": 0.1
    },
    "ai_exposure_index": 0.5,
    "market_risk_score": 0.15,
    "company_risk_score": 0.1,
    "confidence_score": 0.95,
    "archetype": "mature_stable",
    "data_source": "expansion_batch_2026_real",
    "last_updated": "2026-04-28"
  },
  {
    "company_name": "US Foods Holding Corp.",
    "industry": "Food Distribution",
    "company_size": "global_giant",
    "stage": "public",
    "workforce_count": 30000,
    "open_jobs_count": 0,
    "financial_signals": {
      "burn_rate": "moderate",
      "funding_stage": "Public (NASDAQ/NYSE)",
      "revenue_trend": "stable",
      "months_since_last_funding": 120
    },
    "layoff_history": {
      "total_layoffs": 0,
      "last_layoff_date": "No History",
      "layoff_frequency": "none",
      "affected_departments": []
    },
    "hiring_signals": {
      "hiring_velocity": "moderate",
      "hiring_freeze_score": 0.1
    },
    "role_risk_map": {
      "sales": 0.1,
      "designer": 0.1,
      "hr_recruiter": 0.1,
      "data_scientist": 0.1,
      "product_manager": 0.1,
      "software_engineer": 0.1
    },
    "ai_exposure_index": 0.5,
    "market_risk_score": 0.15,
    "company_risk_score": 0.1,
    "confidence_score": 0.95,
    "archetype": "mature_stable",
    "data_source": "expansion_batch_2026_real",
    "last_updated": "2026-04-28"
  },
  {
    "company_name": "Liberty Media Corp",
    "industry": "Entertainment",
    "company_size": "large",
    "stage": "public",
    "workforce_count": 1674,
    "open_jobs_count": 0,
    "financial_signals": {
      "burn_rate": "moderate",
      "funding_stage": "Public (NASDAQ/NYSE)",
      "revenue_trend": "stable",
      "months_since_last_funding": 120
    },
    "layoff_history": {
      "total_layoffs": 0,
      "last_layoff_date": "No History",
      "layoff_frequency": "none",
      "affected_departments": []
    },
    "hiring_signals": {
      "hiring_velocity": "moderate",
      "hiring_freeze_score": 0.1
    },
    "role_risk_map": {
      "sales": 0.1,
      "designer": 0.1,
      "hr_recruiter": 0.1,
      "data_scientist": 0.1,
      "product_manager": 0.1,
      "software_engineer": 0.1
    },
    "ai_exposure_index": 0.5,
    "market_risk_score": 0.15,
    "company_risk_score": 0.1,
    "confidence_score": 0.95,
    "archetype": "mature_stable",
    "data_source": "expansion_batch_2026_real",
    "last_updated": "2026-04-28"
  },
  {
    "company_name": "Snap-on Inc",
    "industry": "Tools & Accessories",
    "company_size": "global_giant",
    "stage": "public",
    "workforce_count": 13000,
    "open_jobs_count": 0,
    "financial_signals": {
      "burn_rate": "moderate",
      "funding_stage": "Public (NASDAQ/NYSE)",
      "revenue_trend": "stable",
      "months_since_last_funding": 120
    },
    "layoff_history": {
      "total_layoffs": 0,
      "last_layoff_date": "No History",
      "layoff_frequency": "none",
      "affected_departments": []
    },
    "hiring_signals": {
      "hiring_velocity": "moderate",
      "hiring_freeze_score": 0.1
    },
    "role_risk_map": {
      "sales": 0.1,
      "designer": 0.1,
      "hr_recruiter": 0.1,
      "data_scientist": 0.1,
      "product_manager": 0.1,
      "software_engineer": 0.1
    },
    "ai_exposure_index": 0.5,
    "market_risk_score": 0.15,
    "company_risk_score": 0.1,
    "confidence_score": 0.95,
    "archetype": "mature_stable",
    "data_source": "expansion_batch_2026_real",
    "last_updated": "2026-04-28"
  },
  {
    "company_name": "CENTENE CORP",
    "industry": "Healthcare Plans",
    "company_size": "global_giant",
    "stage": "public",
    "workforce_count": 61100,
    "open_jobs_count": 0,
    "financial_signals": {
      "burn_rate": "moderate",
      "funding_stage": "Public (NASDAQ/NYSE)",
      "revenue_trend": "stable",
      "months_since_last_funding": 120
    },
    "layoff_history": {
      "total_layoffs": 0,
      "last_layoff_date": "No History",
      "layoff_frequency": "none",
      "affected_departments": []
    },
    "hiring_signals": {
      "hiring_velocity": "moderate",
      "hiring_freeze_score": 0.1
    },
    "role_risk_map": {
      "sales": 0.1,
      "designer": 0.1,
      "hr_recruiter": 0.1,
      "data_scientist": 0.1,
      "product_manager": 0.1,
      "software_engineer": 0.1
    },
    "ai_exposure_index": 0.5,
    "market_risk_score": 0.15,
    "company_risk_score": 0.1,
    "confidence_score": 0.95,
    "archetype": "mature_stable",
    "data_source": "expansion_batch_2026_real",
    "last_updated": "2026-04-28"
  },
  {
    "company_name": "DICK'S SPORTING GOODS, INC.",
    "industry": "Specialty Retail",
    "company_size": "global_giant",
    "stage": "public",
    "workforce_count": 31600,
    "open_jobs_count": 0,
    "financial_signals": {
      "burn_rate": "moderate",
      "funding_stage": "Public (NASDAQ/NYSE)",
      "revenue_trend": "stable",
      "months_since_last_funding": 120
    },
    "layoff_history": {
      "total_layoffs": 0,
      "last_layoff_date": "No History",
      "layoff_frequency": "none",
      "affected_departments": []
    },
    "hiring_signals": {
      "hiring_velocity": "moderate",
      "hiring_freeze_score": 0.1
    },
    "role_risk_map": {
      "sales": 0.1,
      "designer": 0.1,
      "hr_recruiter": 0.1,
      "data_scientist": 0.1,
      "product_manager": 0.1,
      "software_engineer": 0.1
    },
    "ai_exposure_index": 0.5,
    "market_risk_score": 0.15,
    "company_risk_score": 0.1,
    "confidence_score": 0.95,
    "archetype": "mature_stable",
    "data_source": "expansion_batch_2026_real",
    "last_updated": "2026-04-28"
  }
]